[{"id":"6294cc6dad7fd60bbc3f517e","clearanceType":"Runway Change","time":1549641064000,"type":"DEP"},{"id":"6294cc6dad7fd60bbc3f5180","clearanceType":"Runway Entry Change","time":1549641064000,"type":"DEP"},{"id":"6294cc6dad7fd60bbc3f5182","clearanceType":"Runway Change","time":1549641064000,"type":"DEP"},{"id":"6294cc6dad7fd60bbc3f518c","clearanceType":"Runway Entry Change","time":1549641064000,"type":"DEP"},{"id":"6294cc6dad7fd60bbc3f518e","clearanceType":"Runway Change","time":1549641064000,"type":"DEP"},{"id":"6294cc6ead7fd60bbc3f5190","clearanceType":"Runway Entry Change","time":1549641064000,"type":"DEP"},{"id":"6294cc6ead7fd60bbc3f5192","clearanceType":"Runway Change","time":1549641064000,"type":"DEP"},{"id":"6294cc6ead7fd60bbc3f5194","clearanceType":"Runway Entry Change","time":1549641064000,"type":"DEP"},{"id":"6294cc6ead7fd60bbc3f5196","clearanceType":"Runway Change","time":1549641064000,"type":"DEP"},{"id":"6294cc6ead7fd60bbc3f5198","clearanceType":"Runway Entry Change","time":1549641064000,"type":"DEP"},{"id":"6294cc6ead7fd60bbc3f519a","clearanceType":"Runway Change","time":1549641065000,"type":"DEP"},{"id":"6294cc6fad7fd60bbc3f519c","clearanceType":"Runway Entry Change","time":1549641065000,"type":"DEP"},{"id":"6294cc6fad7fd60bbc3f519e","clearanceType":"Runway Change","time":1549641065000,"type":"DEP"},{"id":"6294cc6fad7fd60bbc3f51a0","clearanceType":"Runway Entry Change","time":1549641065000,"type":"DEP"},{"id":"6294cccaad7fd60bbc3f59c0","clearanceType":"Startup Clearance","time":1549641156500,"type":"DEP"},{"id":"6294cccaad7fd60bbc3f59c2","clearanceType":"Startup Clearance","time":1549641157500,"type":"DEP"},{"id":"6294cccaad7fd60bbc3f59c4","clearanceType":"Startup Clearance","time":1549641157500,"type":"DEP"},{"id":"6294cccaad7fd60bbc3f59c6","clearanceType":"Startup Clearance","time":1549641157500,"type":"DEP"},{"id":"6294ccd1ad7fd60bbc3f5a88","clearanceType":"Pushback Clearance","time":1549641164500,"type":"DEP"},{"id":"6294ccd2ad7fd60bbc3f5a8a","clearanceType":"Taxi Clearance","time":1549641164500,"type":"DEP"},{"id":"6294ccd4ad7fd60bbc3f5ac2","clearanceType":"Taxi Clearance","time":1549641166500,"type":"DEP"},{"id":"6294ccd5ad7fd60bbc3f5ade","clearanceType":"Pushback Clearance","time":1549641168500,"type":"DEP"},{"id":"6294ccd6ad7fd60bbc3f5afc","clearanceType":"Taxi Clearance","time":1549641169500,"type":"DEP"},{"id":"6294ccd6ad7fd60bbc3f5b16","clearanceType":"Taxi Clearance","time":1549641169500,"type":"DEP"},{"id":"6294ccf2ad7fd60bbc3f5da4","clearanceType":"Lineup Clearance","time":1549641197500,"type":"DEP"},{"id":"6294cd13ad7fd60bbc3f60be","clearanceType":"Runway Change","time":1549641230600,"type":"DEP"},{"id":"6294cd13ad7fd60bbc3f60c0","clearanceType":"Runway Entry Change","time":1549641230600,"type":"DEP"},{"id":"6294cd50ad7fd60bbc3f66e4","clearanceType":"Takeoff Clearance","time":1549641290600,"type":"DEP"},{"id":"6294cd9fad7fd60bbc3f6efc","clearanceType":"Lineup Clearance","time":1549641369600,"type":"DEP"},{"id":"6294cda6ad7fd60bbc3f6fb6","clearanceType":"Startup Clearance","time":1549641376600,"type":"DEP"},{"id":"6294cdaaad7fd60bbc3f7024","clearanceType":"Pushback Clearance","time":1549641380600,"type":"DEP"},{"id":"6294cdabad7fd60bbc3f7044","clearanceType":"Taxi Clearance","time":1549641381600,"type":"DEP"},{"id":"6294cdbbad7fd60bbc3f71ec","clearanceType":"Taxi Clearance","time":1549641397600,"type":"DEP"},{"id":"6294ce03ad7fd60bbc3f7940","clearanceType":"Runway Change","time":1549641470600,"type":"DEP"},{"id":"6294ce03ad7fd60bbc3f7942","clearanceType":"Runway Entry Change","time":1549641470600,"type":"DEP"},{"id":"6294ce46ad7fd60bbc3f8084","clearanceType":"Startup Clearance","time":1549641537600,"type":"DEP"},{"id":"6294ce6aad7fd60bbc3f8476","clearanceType":"Takeoff Clearance","time":1549641572600,"type":"DEP"},{"id":"6294ce7bad7fd60bbc3f865a","clearanceType":"Runway Change","time":1549641590600,"type":"DEP"},{"id":"6294ce7bad7fd60bbc3f865c","clearanceType":"Runway Entry Change","time":1549641590600,"type":"DEP"},{"id":"6294ce7bad7fd60bbc3f865e","clearanceType":"Runway Change","time":1549641590600,"type":"DEP"},{"id":"6294ce7bad7fd60bbc3f8660","clearanceType":"Runway Entry Change","time":1549641590600,"type":"DEP"},{"id":"6294cebbad7fd60bbc3f8e3e","clearanceType":"Lineup Clearance","time":1549641653600,"type":"DEP"},{"id":"6294cebdad7fd60bbc3f8e80","clearanceType":"Takeoff Clearance","time":1549641655600,"type":"DEP"},{"id":"6294cee4ad7fd60bbc3f936e","clearanceType":"Taxi Clearance","time":1549641695600,"type":"DEP"},{"id":"6294cef8ad7fd60bbc3f95f2","clearanceType":"Startup Clearance","time":1549641715600,"type":"DEP"},{"id":"6294cf07ad7fd60bbc3f97d4","clearanceType":"Taxi Clearance","time":1549641730600,"type":"DEP"},{"id":"6294cf08ad7fd60bbc3f97f8","clearanceType":"Taxi Clearance","time":1549641731600,"type":"DEP"},{"id":"6294cf2fad7fd60bbc3f9ce0","clearanceType":"Runway Change","time":1549641770600,"type":"DEP"},{"id":"6294cf2fad7fd60bbc3f9ce2","clearanceType":"Runway Entry Change","time":1549641770600,"type":"DEP"},{"id":"6294cf6bad7fd60bbc3fa4ca","clearanceType":"Runway Change","time":1549641830600,"type":"DEP"},{"id":"6294cf6bad7fd60bbc3fa4cc","clearanceType":"Runway Entry Change","time":1549641830600,"type":"DEP"},{"id":"6294d05bad7fd60bbc3fc794","clearanceType":"Runway Change","time":1549642070600,"type":"DEP"},{"id":"6294d05bad7fd60bbc3fc796","clearanceType":"Runway Entry Change","time":1549642070600,"type":"DEP"},{"id":"6294d096ad7fd60bbc3fd090","clearanceType":"Startup Clearance","time":1549642129000,"type":"DEP"},{"id":"6294d096ad7fd60bbc3fd0b8","clearanceType":"Startup Clearance","time":1549642129000,"type":"DEP"},{"id":"6294d097ad7fd60bbc3fd0ba","clearanceType":"Startup Clearance","time":1549642130000,"type":"DEP"},{"id":"6294d097ad7fd60bbc3fd0e2","clearanceType":"Startup Clearance","time":1549642130000,"type":"DEP"},{"id":"6294d098ad7fd60bbc3fd0e4","clearanceType":"Startup Clearance","time":1549642131000,"type":"DEP"},{"id":"6294d0a6ad7fd60bbc3fd30a","clearanceType":"Pushback Clearance","time":1549642145000,"type":"DEP"},{"id":"6294d0a7ad7fd60bbc3fd33a","clearanceType":"Pushback Clearance","time":1549642146000,"type":"DEP"},{"id":"6294d0a8ad7fd60bbc3fd36a","clearanceType":"Taxi Clearance","time":1549642147000,"type":"DEP"},{"id":"6294d0a8ad7fd60bbc3fd394","clearanceType":"Pushback Clearance","time":1549642147000,"type":"DEP"},{"id":"6294d0a9ad7fd60bbc3fd39e","clearanceType":"Pushback Clearance","time":1549642148000,"type":"DEP"},{"id":"6294d0aaad7fd60bbc3fd3f0","clearanceType":"Taxi Clearance","time":1549642149000,"type":"DEP"},{"id":"6294d0aaad7fd60bbc3fd3f2","clearanceType":"Taxi Clearance","time":1549642150000,"type":"DEP"},{"id":"6294d0abad7fd60bbc3fd3f4","clearanceType":"Taxi Clearance","time":1549642150000,"type":"DEP"},{"id":"6294d0abad7fd60bbc3fd41e","clearanceType":"Taxi Clearance","time":1549642150000,"type":"DEP"},{"id":"6294d0d2ad7fd60bbc3fda2a","clearanceType":"Runway Change","time":1549642190000,"type":"DEP"},{"id":"6294d0d2ad7fd60bbc3fda2c","clearanceType":"Runway Entry Change","time":1549642190000,"type":"DEP"},{"id":"6294d0dbad7fd60bbc3fdb66","clearanceType":"Taxi Clearance","time":1549642198000,"type":"DEP"},{"id":"6294d208ad7fd60bbc400c30","clearanceType":"Taxi Clearance","time":1549642499100,"type":"DEP"},{"id":"6294d214ad7fd60bbc400e0e","clearanceType":"Lineup Clearance","time":1549642511100,"type":"DEP"},{"id":"6294d217ad7fd60bbc400e8a","clearanceType":"Takeoff Clearance","time":1549642514100,"type":"DEP"},{"id":"6294d21fad7fd60bbc400fca","clearanceType":"Taxi Clearance","time":1549642522100,"type":"DEP"},{"id":"6294d223ad7fd60bbc40108e","clearanceType":"Runway Entry Change","time":1549642526100,"type":"DEP"},{"id":"6294d22fad7fd60bbc401238","clearanceType":"Runway Entry Change","time":1549642538100,"type":"DEP"},{"id":"6294d232ad7fd60bbc4012b0","clearanceType":"Runway Entry Change","time":1549642541100,"type":"DEP"},{"id":"6294d236ad7fd60bbc40134a","clearanceType":"Lineup Clearance","time":1549642545100,"type":"DEP"},{"id":"6294d259ad7fd60bbc40188c","clearanceType":"Takeoff Clearance","time":1549642580100,"type":"DEP"},{"id":"6294d271ad7fd60bbc401c46","clearanceType":"Lineup Clearance","time":1549642604100,"type":"DEP"},{"id":"6294d276ad7fd60bbc401d06","clearanceType":"Lineup Clearance","time":1549642609100,"type":"DEP"},{"id":"6294d290ad7fd60bbc4020d8","clearanceType":"Takeoff Clearance","time":1549642635100,"type":"DEP"},{"id":"6294d2b2ad7fd60bbc4025ee","clearanceType":"Lineup Clearance","time":1549642669100,"type":"DEP"},{"id":"6294d2bdad7fd60bbc4027bc","clearanceType":"Lineup Clearance","time":1549642680100,"type":"DEP"},{"id":"6294d2c4ad7fd60bbc4028aa","clearanceType":"Takeoff Clearance","time":1549642687100,"type":"DEP"},{"id":"6294d2eead7fd60bbc402f20","clearanceType":"Runway Change","time":1549642730100,"type":"DEP"},{"id":"6294d2efad7fd60bbc402f22","clearanceType":"Runway Entry Change","time":1549642730100,"type":"DEP"},{"id":"6294d2efad7fd60bbc402f24","clearanceType":"Runway Change","time":1549642730100,"type":"DEP"},{"id":"6294d2efad7fd60bbc402f26","clearanceType":"Runway Entry Change","time":1549642730100,"type":"DEP"},{"id":"6294d2faad7fd60bbc4030fa","clearanceType":"Takeoff Clearance","time":1549642741100,"type":"DEP"},{"id":"6294d334ad7fd60bbc403a5a","clearanceType":"Takeoff Clearance","time":1549642799100,"type":"DEP"},{"id":"6294d360ad7fd60bbc404172","clearanceType":"Lineup Clearance","time":1549642843100,"type":"DEP"},{"id":"6294d389ad7fd60bbc4047b4","clearanceType":"Lineup Clearance","time":1549642884100,"type":"DEP"},{"id":"6294d38bad7fd60bbc404806","clearanceType":"Lineup Clearance","time":1549642886100,"type":"DEP"},{"id":"6294d38cad7fd60bbc404830","clearanceType":"Takeoff Clearance","time":1549642887100,"type":"DEP"},{"id":"6294d3a2ad7fd60bbc404bd0","clearanceType":"Runway Change","time":1549642910100,"type":"DEP"},{"id":"6294d3a3ad7fd60bbc404bd2","clearanceType":"Runway Entry Change","time":1549642910100,"type":"DEP"},{"id":"6294d3b7ad7fd60bbc404f38","clearanceType":"Lineup Clearance","time":1549642930100,"type":"DEP"},{"id":"6294d3d7ad7fd60bbc405486","clearanceType":"Takeoff Clearance","time":1549642962100,"type":"DEP"},{"id":"6294d3fdad7fd60bbc405a94","clearanceType":"Lineup Clearance","time":1549643000100,"type":"DEP"},{"id":"6294d414ad7fd60bbc405e58","clearanceType":"Taxi Clearance","time":1549643023100,"type":"DEP"},{"id":"6294d41aad7fd60bbc405f24","clearanceType":"Takeoff Clearance","time":1549643029100,"type":"DEP"},{"id":"6294d41aad7fd60bbc405f4e","clearanceType":"Runway Change","time":1549643030100,"type":"DEP"},{"id":"6294d41bad7fd60bbc405f50","clearanceType":"Runway Entry Change","time":1549643030100,"type":"DEP"}]