[{"entityId":"CRITICAL_ASSET_1648218212724","entityName":"R35R","droneId":"Ybi96h1N3MxAHlwmMkoN","droneName":"Drone_02","eventType":"DRONE_VS_CA","description":"drone vs critical asset","riskType":"YELLOW","distance":1382.73,"timestamp":1549641198000,"visible":true,"id":"627241d081a14320800acee6"},{"entityId":"CRITICAL_ASSET_1648218212724","entityName":"R35R","droneId":"Ybi96h1N3MxAHlwmMkoN","droneName":"Drone_02","eventType":"DRONE_VS_CA","description":"drone vs critical asset","riskType":"YELLOW","distance":1372.15,"timestamp":1549641204000,"visible":true,"id":"627241d681a14320800acf70"},{"entityId":"CRITICAL_ASSET_1648218212724","entityName":"R35R","droneId":"Ybi96h1N3MxAHlwmMkoN","droneName":"Drone_02","eventType":"DRONE_VS_CA","description":"drone vs critical asset","riskType":"YELLOW","distance":1286.36,"timestamp":1549641264000,"visible":true,"id":"6272421281a14320800ad506"},{"entityId":"CRITICAL_ASSET_1648218212724","entityName":"R35R","droneId":"Ybi96h1N3MxAHlwmMkoN","droneName":"Drone_02","eventType":"DRONE_VS_CA","description":"drone vs critical asset","riskType":"YELLOW","distance":1284.18,"timestamp":1549641266000,"visible":false,"id":"6272421481a14320800ad53a"},{"entityId":"CRITICAL_ASSET_1648218568249","entityName":"FINGER1","droneId":"8UMYEPnM84a7SSLnqZ95","droneName":"Drone_04","eventType":"DRONE_VS_CA","description":"drone vs critical asset","riskType":"YELLOW","distance":56.29,"timestamp":1549641732000,"visible":true,"id":"627243e681a14320800b0550"},{"entityId":"CRITICAL_ASSET_1648218568249","entityName":"FINGER1","droneId":"8UMYEPnM84a7SSLnqZ95","droneName":"Drone_04","eventType":"DRONE_VS_CA","description":"drone vs critical asset","riskType":"RED","distance":29.52,"timestamp":1549641743000,"visible":false,"id":"627243f181a14320800b06a0"},{"entityId":"CRITICAL_ASSET_1648218568249","entityName":"FINGER1","droneId":"8UMYEPnM84a7SSLnqZ95","droneName":"Drone_04","eventType":"DRONE_VS_CA","description":"drone vs critical asset","riskType":"RED","distance":26.51,"timestamp":1549641752000,"visible":true,"id":"627243fa81a14320800b07bc"},{"entityId":"CRITICAL_ASSET_1648220220216","entityName":"35L_DEP","droneId":"RvwembwLgIdcb5W1WWmU","droneName":"Drone_01","eventType":"DRONE_VS_CA","description":"drone vs critical asset","riskType":"YELLOW","distance":1962.63,"timestamp":1549642243000,"visible":true,"id":"627245e581a14320800b4a2c"},{"entityId":"CRITICAL_ASSET_1648220220216","entityName":"35L_DEP","droneId":"RvwembwLgIdcb5W1WWmU","droneName":"Drone_01","eventType":"DRONE_VS_CA","description":"drone vs critical asset","riskType":"YELLOW","distance":1947.63,"timestamp":1549642246000,"visible":true,"id":"627245e881a14320800b4aa2"},{"entityId":"CRITICAL_ASSET_1648220220216","entityName":"35L_DEP","droneId":"RvwembwLgIdcb5W1WWmU","droneName":"Drone_01","eventType":"DRONE_VS_CA","description":"drone vs critical asset","riskType":"YELLOW","distance":1907.63,"timestamp":1549642254000,"visible":true,"id":"627245f081a14320800b4bda"},{"entityId":"CRITICAL_ASSET_1648220220216","entityName":"35L_DEP","droneId":"RvwembwLgIdcb5W1WWmU","droneName":"Drone_01","eventType":"DRONE_VS_CA","description":"drone vs critical asset","riskType":"YELLOW","distance":1802.63,"timestamp":1549642275000,"visible":false,"id":"6272460581a14320800b4f08"},{"entityId":"CRITICAL_ASSET_1648220220216","entityName":"35L_DEP","droneId":"RvwembwLgIdcb5W1WWmU","droneName":"Drone_01","eventType":"DRONE_VS_CA","description":"drone vs critical asset","riskType":"YELLOW","distance":1772.64,"timestamp":1549642281000,"visible":false,"id":"6272460b81a14320800b4ff4"},{"entityId":"CRITICAL_ASSET_1648220220216","entityName":"35L_DEP","droneId":"RvwembwLgIdcb5W1WWmU","droneName":"Drone_01","eventType":"DRONE_VS_CA","description":"drone vs critical asset","riskType":"YELLOW","distance":1712.64,"timestamp":1549642293000,"visible":false,"id":"6272461781a14320800b51cc"},{"entityId":"CRITICAL_ASSET_1648220220216","entityName":"35L_DEP","droneId":"RvwembwLgIdcb5W1WWmU","droneName":"Drone_01","eventType":"DRONE_VS_CA","description":"drone vs critical asset","riskType":"YELLOW","distance":1702.64,"timestamp":1549642295000,"visible":false,"id":"6272461981a14320800b5220"},{"entityId":"CRITICAL_ASSET_1648220220216","entityName":"35L_DEP","droneId":"RvwembwLgIdcb5W1WWmU","droneName":"Drone_01","eventType":"DRONE_VS_CA","description":"drone vs critical asset","riskType":"YELLOW","distance":1662.64,"timestamp":1549642303000,"visible":true,"id":"6272462181a14320800b535c"},{"entityId":"CRITICAL_ASSET_1648220220216","entityName":"35L_DEP","droneId":"RvwembwLgIdcb5W1WWmU","droneName":"Drone_01","eventType":"DRONE_VS_CA","description":"drone vs critical asset","riskType":"YELLOW","distance":1647.64,"timestamp":1549642306000,"visible":true,"id":"6272462481a14320800b53d2"},{"entityId":"CRITICAL_ASSET_1648220220216","entityName":"35L_DEP","droneId":"RvwembwLgIdcb5W1WWmU","droneName":"Drone_01","eventType":"DRONE_VS_CA","description":"drone vs critical asset","riskType":"YELLOW","distance":1632.64,"timestamp":1549642309000,"visible":true,"id":"6272462781a14320800b544a"},{"entityId":"CRITICAL_ASSET_1648220220216","entityName":"35L_DEP","droneId":"RvwembwLgIdcb5W1WWmU","droneName":"Drone_01","eventType":"DRONE_VS_CA","description":"drone vs critical asset","riskType":"YELLOW","distance":1607.64,"timestamp":1549642314000,"visible":true,"id":"6272462c81a14320800b550c"},{"entityId":"CRITICAL_ASSET_1648220220216","entityName":"35L_DEP","droneId":"RvwembwLgIdcb5W1WWmU","droneName":"Drone_01","eventType":"DRONE_VS_CA","description":"drone vs critical asset","riskType":"YELLOW","distance":1587.64,"timestamp":1549642318000,"visible":false,"id":"6272463081a14320800b55a8"},{"entityId":"CRITICAL_ASSET_1648220220216","entityName":"35L_DEP","droneId":"RvwembwLgIdcb5W1WWmU","droneName":"Drone_01","eventType":"DRONE_VS_CA","description":"drone vs critical asset","riskType":"ORANGE","distance":1547.64,"timestamp":1549642326000,"visible":false,"id":"6272463881a14320800b56dc"},{"entityId":"CRITICAL_ASSET_1648220220216","entityName":"35L_DEP","droneId":"RvwembwLgIdcb5W1WWmU","droneName":"Drone_01","eventType":"DRONE_VS_CA","description":"drone vs critical asset","riskType":"ORANGE","distance":1507.65,"timestamp":1549642334000,"visible":false,"id":"6272464081a14320800b581c"},{"entityId":"CRITICAL_ASSET_1648220220216","entityName":"35L_DEP","droneId":"RvwembwLgIdcb5W1WWmU","droneName":"Drone_01","eventType":"DRONE_VS_CA","description":"drone vs critical asset","riskType":"RED","distance":1377.65,"timestamp":1549642360000,"visible":true,"id":"6272465a81a14320800b5c16"},{"entityId":"CRITICAL_ASSET_1648220220216","entityName":"35L_DEP","droneId":"RvwembwLgIdcb5W1WWmU","droneName":"Drone_01","eventType":"DRONE_VS_CA","description":"drone vs critical asset","riskType":"RED","distance":1362.65,"timestamp":1549642363000,"visible":true,"id":"6272465d81a14320800b5c90"},{"entityId":"CRITICAL_ASSET_1648220220216","entityName":"35L_DEP","droneId":"RvwembwLgIdcb5W1WWmU","droneName":"Drone_01","eventType":"DRONE_VS_CA","description":"drone vs critical asset","riskType":"RED","distance":1232.66,"timestamp":1549642389000,"visible":false,"id":"6272467781a14320800b605a"},{"entityId":"CRITICAL_ASSET_1648220220216","entityName":"35L_DEP","droneId":"RvwembwLgIdcb5W1WWmU","droneName":"Drone_01","eventType":"DRONE_VS_CA","description":"drone vs critical asset","riskType":"RED","distance":1227.66,"timestamp":1549642390000,"visible":true,"id":"6272467881a14320800b6080"},{"entityId":"CRITICAL_ASSET_1648220220216","entityName":"35L_DEP","droneId":"RvwembwLgIdcb5W1WWmU","droneName":"Drone_01","eventType":"DRONE_VS_CA","description":"drone vs critical asset","riskType":"RED","distance":1197.67,"timestamp":1549642396000,"visible":true,"id":"6272467e81a14320800b615c"},{"entityId":"CRITICAL_ASSET_1648220220216","entityName":"35L_DEP","droneId":"RvwembwLgIdcb5W1WWmU","droneName":"Drone_01","eventType":"DRONE_VS_CA","description":"drone vs critical asset","riskType":"RED","distance":1122.67,"timestamp":1549642411000,"visible":false,"id":"6272468d81a14320800b6380"},{"entityId":"CRITICAL_ASSET_1648220220216","entityName":"35L_DEP","droneId":"RvwembwLgIdcb5W1WWmU","droneName":"Drone_01","eventType":"DRONE_VS_CA","description":"drone vs critical asset","riskType":"RED","distance":1042.68,"timestamp":1549642427000,"visible":false,"id":"6272469d81a14320800b65c4"},{"entityId":"CRITICAL_ASSET_1648220220216","entityName":"35L_DEP","droneId":"RvwembwLgIdcb5W1WWmU","droneName":"Drone_01","eventType":"DRONE_VS_CA","description":"drone vs critical asset","riskType":"RED","distance":962.69,"timestamp":1549642443000,"visible":false,"id":"627246ad81a14320800b680a"},{"entityId":"CRITICAL_ASSET_1648220220216","entityName":"35L_DEP","droneId":"nX6JBA3QdiTF5OnMP3gs","droneName":"Drone_03","eventType":"DRONE_VS_CA","description":"drone vs critical asset","riskType":"YELLOW","distance":1234.84,"timestamp":1549642444000,"visible":false,"id":"627246ae81a14320800b6832"},{"entityId":"CRITICAL_ASSET_1648220220216","entityName":"35L_DEP","droneId":"nX6JBA3QdiTF5OnMP3gs","droneName":"Drone_03","eventType":"DRONE_VS_CA","description":"drone vs critical asset","riskType":"YELLOW","distance":1232.5,"timestamp":1549642446000,"visible":true,"id":"627246b081a14320800b687c"},{"entityId":"CRITICAL_ASSET_1648217782833","entityName":"R35L","droneId":"nX6JBA3QdiTF5OnMP3gs","droneName":"Drone_03","eventType":"DRONE_VS_CA","description":"drone vs critical asset","riskType":"YELLOW","distance":1783.05,"timestamp":1549642446000,"visible":true,"id":"627246b081a14320800b687e"},{"entityId":"CRITICAL_ASSET_1648220220216","entityName":"35L_DEP","droneId":"RvwembwLgIdcb5W1WWmU","droneName":"Drone_01","eventType":"DRONE_VS_CA","description":"drone vs critical asset","riskType":"RED","distance":937.69,"timestamp":1549642448000,"visible":true,"id":"627246b281a14320800b68ce"},{"entityId":"CRITICAL_ASSET_1648220220216","entityName":"35L_DEP","droneId":"RvwembwLgIdcb5W1WWmU","droneName":"Drone_01","eventType":"DRONE_VS_CA","description":"drone vs critical asset","riskType":"RED","distance":932.69,"timestamp":1549642449000,"visible":false,"id":"627246b381a14320800b68f4"},{"entityId":"CRITICAL_ASSET_1648220220216","entityName":"35L_DEP","droneId":"RvwembwLgIdcb5W1WWmU","droneName":"Drone_01","eventType":"DRONE_VS_CA","description":"drone vs critical asset","riskType":"RED","distance":917.69,"timestamp":1549642452000,"visible":true,"id":"627246b681a14320800b6966"},{"entityId":"CRITICAL_ASSET_1648220220216","entityName":"35L_DEP","droneId":"RvwembwLgIdcb5W1WWmU","droneName":"Drone_01","eventType":"DRONE_VS_CA","description":"drone vs critical asset","riskType":"RED","distance":892.7,"timestamp":1549642457000,"visible":true,"id":"627246bb81a14320800b6a1e"},{"entityId":"CRITICAL_ASSET_1648220220216","entityName":"35L_DEP","droneId":"RvwembwLgIdcb5W1WWmU","droneName":"Drone_01","eventType":"DRONE_VS_CA","description":"drone vs critical asset","riskType":"RED","distance":832.71,"timestamp":1549642469000,"visible":false,"id":"627246c781a14320800b6bdc"},{"entityId":"CRITICAL_ASSET_1648220220216","entityName":"35L_DEP","droneId":"RvwembwLgIdcb5W1WWmU","droneName":"Drone_01","eventType":"DRONE_VS_CA","description":"drone vs critical asset","riskType":"RED","distance":762.72,"timestamp":1549642483000,"visible":true,"id":"627246d581a14320800b6de2"},{"entityId":"CRITICAL_ASSET_1648217782833","entityName":"R35L","droneId":"nX6JBA3QdiTF5OnMP3gs","droneName":"Drone_03","eventType":"DRONE_VS_CA","description":"drone vs critical asset","riskType":"YELLOW","distance":1760.78,"timestamp":1549642488000,"visible":true,"id":"627246da81a14320800b6ea2"},{"entityId":"CRITICAL_ASSET_1648217782833","entityName":"R35L","droneId":"nX6JBA3QdiTF5OnMP3gs","droneName":"Drone_03","eventType":"DRONE_VS_CA","description":"drone vs critical asset","riskType":"YELLOW","distance":1758.76,"timestamp":1549642493000,"visible":false,"id":"627246df81a14320800b6f5c"},{"entityId":"CRITICAL_ASSET_1648220220216","entityName":"35L_DEP","droneId":"nX6JBA3QdiTF5OnMP3gs","droneName":"Drone_03","eventType":"DRONE_VS_CA","description":"drone vs critical asset","riskType":"YELLOW","distance":1184.84,"timestamp":1549642493000,"visible":false,"id":"627246df81a14320800b6f5e"},{"entityId":"CRITICAL_ASSET_1648220220216","entityName":"35L_DEP","droneId":"RvwembwLgIdcb5W1WWmU","droneName":"Drone_01","eventType":"DRONE_VS_CA","description":"drone vs critical asset","riskType":"RED","distance":657.74,"timestamp":1549642504000,"visible":true,"id":"627246ea81a14320800b70fc"},{"entityId":"CRITICAL_ASSET_1648220220216","entityName":"35L_DEP","droneId":"RvwembwLgIdcb5W1WWmU","droneName":"Drone_01","eventType":"DRONE_VS_CA","description":"drone vs critical asset","riskType":"RED","distance":652.74,"timestamp":1549642505000,"visible":false,"id":"627246eb81a14320800b7122"},{"entityId":"CRITICAL_ASSET_1648220220216","entityName":"35L_DEP","droneId":"RvwembwLgIdcb5W1WWmU","droneName":"Drone_01","eventType":"DRONE_VS_CA","description":"drone vs critical asset","riskType":"RED","distance":647.74,"timestamp":1549642506000,"visible":true,"id":"627246ec81a14320800b7148"},{"entityId":"CRITICAL_ASSET_1648220220216","entityName":"35L_DEP","droneId":"RvwembwLgIdcb5W1WWmU","droneName":"Drone_01","eventType":"DRONE_VS_CA","description":"drone vs critical asset","riskType":"RED","distance":627.75,"timestamp":1549642510000,"visible":false,"id":"627246f081a14320800b71da"},{"entityId":"CRITICAL_ASSET_1648220220216","entityName":"35L_DEP","droneId":"RvwembwLgIdcb5W1WWmU","droneName":"Drone_01","eventType":"DRONE_VS_CA","description":"drone vs critical asset","riskType":"RED","distance":622.75,"timestamp":1549642511000,"visible":true,"id":"627246f181a14320800b7200"},{"entityId":"CRITICAL_ASSET_1648220220216","entityName":"35L_DEP","droneId":"RvwembwLgIdcb5W1WWmU","droneName":"Drone_01","eventType":"DRONE_VS_CA","description":"drone vs critical asset","riskType":"RED","distance":617.75,"timestamp":1549642512000,"visible":false,"id":"627246f281a14320800b7226"},{"entityId":"CRITICAL_ASSET_1648220220216","entityName":"35L_DEP","droneId":"RvwembwLgIdcb5W1WWmU","droneName":"Drone_01","eventType":"DRONE_VS_CA","description":"drone vs critical asset","riskType":"RED","distance":407.84,"timestamp":1549642554000,"visible":false,"id":"6272471c81a14320800b782c"},{"entityId":"CRITICAL_ASSET_1648220220216","entityName":"35L_DEP","droneId":"RvwembwLgIdcb5W1WWmU","droneName":"Drone_01","eventType":"DRONE_VS_CA","description":"drone vs critical asset","riskType":"RED","distance":317.91,"timestamp":1549642572000,"visible":false,"id":"6272472e81a14320800b7ac0"},{"entityId":"CRITICAL_ASSET_1648220220216","entityName":"35L_DEP","droneId":"RvwembwLgIdcb5W1WWmU","droneName":"Drone_01","eventType":"DRONE_VS_CA","description":"drone vs critical asset","riskType":"RED","distance":193.13,"timestamp":1549642597000,"visible":false,"id":"6272474781a14320800b7e50"},{"entityId":"CRITICAL_ASSET_1648220220216","entityName":"35L_DEP","droneId":"RvwembwLgIdcb5W1WWmU","droneName":"Drone_01","eventType":"DRONE_VS_CA","description":"drone vs critical asset","riskType":"RED","distance":188.15,"timestamp":1549642598000,"visible":true,"id":"6272474881a14320800b7e76"},{"entityId":"CRITICAL_ASSET_1648220220216","entityName":"35L_DEP","droneId":"RvwembwLgIdcb5W1WWmU","droneName":"Drone_01","eventType":"DRONE_VS_CA","description":"drone vs critical asset","riskType":"RED","distance":158.25,"timestamp":1549642604000,"visible":false,"id":"6272474e81a14320800b7f54"},{"entityId":"CRITICAL_ASSET_1648220220216","entityName":"35L_DEP","droneId":"RvwembwLgIdcb5W1WWmU","droneName":"Drone_01","eventType":"DRONE_VS_CA","description":"drone vs critical asset","riskType":"RED","distance":113.52,"timestamp":1549642613000,"visible":true,"id":"6272475781a14320800b80a4"},{"entityId":"CRITICAL_ASSET_1648220220216","entityName":"35L_DEP","droneId":"RvwembwLgIdcb5W1WWmU","droneName":"Drone_01","eventType":"DRONE_VS_CA","description":"drone vs critical asset","riskType":"RED","distance":103.62,"timestamp":1549642615000,"visible":false,"id":"6272475981a14320800b80ee"},{"entityId":"CRITICAL_ASSET_1648220220216","entityName":"35L_DEP","droneId":"RvwembwLgIdcb5W1WWmU","droneName":"Drone_01","eventType":"DRONE_VS_CA","description":"drone vs critical asset","riskType":"RED","distance":64.27,"timestamp":1549642623000,"visible":true,"id":"6272476181a14320800b8214"},{"entityId":"CRITICAL_ASSET_1648220220216","entityName":"35L_DEP","droneId":"RvwembwLgIdcb5W1WWmU","droneName":"Drone_01","eventType":"DRONE_VS_CA","description":"drone vs critical asset","riskType":"RED","distance":123.3,"timestamp":1549642660000,"visible":false,"id":"6272478681a14320800b8756"},{"entityId":"CRITICAL_ASSET_1648220220216","entityName":"35L_DEP","droneId":"RvwembwLgIdcb5W1WWmU","droneName":"Drone_01","eventType":"DRONE_VS_CA","description":"drone vs critical asset","riskType":"RED","distance":128.26,"timestamp":1549642661000,"visible":true,"id":"6272478781a14320800b877c"},{"entityId":"CRITICAL_ASSET_1648220220216","entityName":"35L_DEP","droneId":"RvwembwLgIdcb5W1WWmU","droneName":"Drone_01","eventType":"DRONE_VS_CA","description":"drone vs critical asset","riskType":"RED","distance":153.13,"timestamp":1549642666000,"visible":false,"id":"6272478c81a14320800b8836"},{"entityId":"CRITICAL_ASSET_1648220220216","entityName":"35L_DEP","droneId":"RvwembwLgIdcb5W1WWmU","droneName":"Drone_01","eventType":"DRONE_VS_CA","description":"drone vs critical asset","riskType":"RED","distance":163.08,"timestamp":1549642668000,"visible":false,"id":"6272478e81a14320800b8882"},{"entityId":"CRITICAL_ASSET_1648220220216","entityName":"35L_DEP","droneId":"RvwembwLgIdcb5W1WWmU","droneName":"Drone_01","eventType":"DRONE_VS_CA","description":"drone vs critical asset","riskType":"RED","distance":188,"timestamp":1549642673000,"visible":false,"id":"6272479381a14320800b893a"},{"entityId":"CRITICAL_ASSET_1648220220216","entityName":"35L_DEP","droneId":"RvwembwLgIdcb5W1WWmU","droneName":"Drone_01","eventType":"DRONE_VS_CA","description":"drone vs critical asset","riskType":"RED","distance":222.91,"timestamp":1549642680000,"visible":false,"id":"6272479a81a14320800b8a3e"},{"entityId":"CRITICAL_ASSET_1648220220216","entityName":"35L_DEP","droneId":"RvwembwLgIdcb5W1WWmU","droneName":"Drone_01","eventType":"DRONE_VS_CA","description":"drone vs critical asset","riskType":"RED","distance":242.87,"timestamp":1549642684000,"visible":true,"id":"6272479e81a14320800b8ad4"},{"entityId":"CRITICAL_ASSET_1648220220216","entityName":"35L_DEP","droneId":"RvwembwLgIdcb5W1WWmU","droneName":"Drone_01","eventType":"DRONE_VS_CA","description":"drone vs critical asset","riskType":"RED","distance":277.81,"timestamp":1549642691000,"visible":true,"id":"627247a581a14320800b8bca"},{"entityId":"CRITICAL_ASSET_1648220220216","entityName":"35L_DEP","droneId":"RvwembwLgIdcb5W1WWmU","droneName":"Drone_01","eventType":"DRONE_VS_CA","description":"drone vs critical asset","riskType":"RED","distance":297.79,"timestamp":1549642695000,"visible":true,"id":"627247a981a14320800b8c56"},{"entityId":"CRITICAL_ASSET_1648220220216","entityName":"35L_DEP","droneId":"RvwembwLgIdcb5W1WWmU","droneName":"Drone_01","eventType":"DRONE_VS_CA","description":"drone vs critical asset","riskType":"RED","distance":302.78,"timestamp":1549642696000,"visible":false,"id":"627247aa81a14320800b8c7a"},{"entityId":"CRITICAL_ASSET_1648217782833","entityName":"R35L","droneId":"RvwembwLgIdcb5W1WWmU","droneName":"Drone_01","eventType":"DRONE_VS_CA","description":"drone vs critical asset","riskType":"YELLOW","distance":2533.37,"timestamp":1549642705000,"visible":false,"id":"627247b381a14320800b8dba"},{"entityId":"CRITICAL_ASSET_1648218212724","entityName":"R35R","droneId":"Ybi96h1N3MxAHlwmMkoN","droneName":"Drone_02","eventType":"DRONE_VS_CA","description":"drone vs critical asset","riskType":"YELLOW","distance":1373.89,"timestamp":1549641203000,"visible":false,"id":"627241d581a14320800acf56"},{"entityId":"CRITICAL_ASSET_1648218212724","entityName":"R35R","droneId":"Ybi96h1N3MxAHlwmMkoN","droneName":"Drone_02","eventType":"DRONE_VS_CA","description":"drone vs critical asset","riskType":"YELLOW","distance":1368.7,"timestamp":1549641206000,"visible":false,"id":"627241d881a14320800acf9e"},{"entityId":"CRITICAL_ASSET_1648218212724","entityName":"R35R","droneId":"Ybi96h1N3MxAHlwmMkoN","droneName":"Drone_02","eventType":"DRONE_VS_CA","description":"drone vs critical asset","riskType":"YELLOW","distance":1350.41,"timestamp":1549641217000,"visible":false,"id":"627241e381a14320800ad09a"},{"entityId":"CRITICAL_ASSET_1648218212724","entityName":"R35R","droneId":"Ybi96h1N3MxAHlwmMkoN","droneName":"Drone_02","eventType":"DRONE_VS_CA","description":"drone vs critical asset","riskType":"YELLOW","distance":1313.38,"timestamp":1549641242000,"visible":true,"id":"627241fc81a14320800ad2dc"},{"entityId":"CRITICAL_ASSET_1648218212724","entityName":"R35R","droneId":"Ybi96h1N3MxAHlwmMkoN","droneName":"Drone_02","eventType":"DRONE_VS_CA","description":"drone vs critical asset","riskType":"YELLOW","distance":1289.73,"timestamp":1549641261000,"visible":false,"id":"6272420f81a14320800ad4b8"},{"entityId":"CRITICAL_ASSET_1648218212724","entityName":"R35R","droneId":"Ybi96h1N3MxAHlwmMkoN","droneName":"Drone_02","eventType":"DRONE_VS_CA","description":"drone vs critical asset","riskType":"YELLOW","distance":1288.6,"timestamp":1549641262000,"visible":true,"id":"6272421081a14320800ad4d2"},{"entityId":"CRITICAL_ASSET_1648218212724","entityName":"R35R","droneId":"Ybi96h1N3MxAHlwmMkoN","droneName":"Drone_02","eventType":"DRONE_VS_CA","description":"drone vs critical asset","riskType":"YELLOW","distance":1287.47,"timestamp":1549641263000,"visible":false,"id":"6272421181a14320800ad4ec"},{"entityId":"CRITICAL_ASSET_1648218568249","entityName":"FINGER1","droneId":"8UMYEPnM84a7SSLnqZ95","droneName":"Drone_04","eventType":"DRONE_VS_CA","description":"drone vs critical asset","riskType":"RED","distance":38.14,"timestamp":1549641739000,"visible":true,"id":"627243ed81a14320800b0626"},{"entityId":"CRITICAL_ASSET_1648218568249","entityName":"FINGER1","droneId":"8UMYEPnM84a7SSLnqZ95","droneName":"Drone_04","eventType":"DRONE_VS_CA","description":"drone vs critical asset","riskType":"RED","distance":27.77,"timestamp":1549641744000,"visible":true,"id":"627243f281a14320800b06c0"},{"entityId":"CRITICAL_ASSET_1648218568249","entityName":"FINGER1","droneId":"8UMYEPnM84a7SSLnqZ95","droneName":"Drone_04","eventType":"DRONE_VS_CA","description":"drone vs critical asset","riskType":"RED","distance":24.39,"timestamp":1549641750000,"visible":true,"id":"627243f881a14320800b077a"},{"entityId":"CRITICAL_ASSET_1648220220216","entityName":"35L_DEP","droneId":"RvwembwLgIdcb5W1WWmU","droneName":"Drone_01","eventType":"DRONE_VS_CA","description":"drone vs critical asset","riskType":"YELLOW","distance":1897.63,"timestamp":1549642256000,"visible":false,"id":"627245f281a14320800b4c28"},{"entityId":"CRITICAL_ASSET_1648220220216","entityName":"35L_DEP","droneId":"RvwembwLgIdcb5W1WWmU","droneName":"Drone_01","eventType":"DRONE_VS_CA","description":"drone vs critical asset","riskType":"YELLOW","distance":1882.63,"timestamp":1549642259000,"visible":false,"id":"627245f581a14320800b4ca0"},{"entityId":"CRITICAL_ASSET_1648220220216","entityName":"35L_DEP","droneId":"RvwembwLgIdcb5W1WWmU","droneName":"Drone_01","eventType":"DRONE_VS_CA","description":"drone vs critical asset","riskType":"YELLOW","distance":1852.63,"timestamp":1549642265000,"visible":true,"id":"627245fb81a14320800b4d8a"},{"entityId":"CRITICAL_ASSET_1648220220216","entityName":"35L_DEP","droneId":"RvwembwLgIdcb5W1WWmU","droneName":"Drone_01","eventType":"DRONE_VS_CA","description":"drone vs critical asset","riskType":"YELLOW","distance":1707.64,"timestamp":1549642294000,"visible":true,"id":"6272461881a14320800b51f4"},{"entityId":"CRITICAL_ASSET_1648220220216","entityName":"35L_DEP","droneId":"RvwembwLgIdcb5W1WWmU","droneName":"Drone_01","eventType":"DRONE_VS_CA","description":"drone vs critical asset","riskType":"YELLOW","distance":1697.64,"timestamp":1549642296000,"visible":true,"id":"6272461a81a14320800b5248"},{"entityId":"CRITICAL_ASSET_1648220220216","entityName":"35L_DEP","droneId":"RvwembwLgIdcb5W1WWmU","droneName":"Drone_01","eventType":"DRONE_VS_CA","description":"drone vs critical asset","riskType":"YELLOW","distance":1622.64,"timestamp":1549642311000,"visible":false,"id":"6272462981a14320800b5498"},{"entityId":"CRITICAL_ASSET_1648220220216","entityName":"35L_DEP","droneId":"RvwembwLgIdcb5W1WWmU","droneName":"Drone_01","eventType":"DRONE_VS_CA","description":"drone vs critical asset","riskType":"ORANGE","distance":1502.65,"timestamp":1549642335000,"visible":true,"id":"6272464181a14320800b5844"},{"entityId":"CRITICAL_ASSET_1648220220216","entityName":"35L_DEP","droneId":"RvwembwLgIdcb5W1WWmU","droneName":"Drone_01","eventType":"DRONE_VS_CA","description":"drone vs critical asset","riskType":"ORANGE","distance":1442.65,"timestamp":1549642347000,"visible":false,"id":"6272464d81a14320800b5a1c"},{"entityId":"CRITICAL_ASSET_1648220220216","entityName":"35L_DEP","droneId":"RvwembwLgIdcb5W1WWmU","droneName":"Drone_01","eventType":"DRONE_VS_CA","description":"drone vs critical asset","riskType":"RED","distance":1297.66,"timestamp":1549642376000,"visible":false,"id":"6272466a81a14320800b5e7a"},{"entityId":"CRITICAL_ASSET_1648220220216","entityName":"35L_DEP","droneId":"RvwembwLgIdcb5W1WWmU","droneName":"Drone_01","eventType":"DRONE_VS_CA","description":"drone vs critical asset","riskType":"RED","distance":1282.66,"timestamp":1549642379000,"visible":true,"id":"6272466d81a14320800b5ee8"},{"entityId":"CRITICAL_ASSET_1648220220216","entityName":"35L_DEP","droneId":"RvwembwLgIdcb5W1WWmU","droneName":"Drone_01","eventType":"DRONE_VS_CA","description":"drone vs critical asset","riskType":"RED","distance":1252.66,"timestamp":1549642385000,"visible":true,"id":"6272467381a14320800b5fc8"},{"entityId":"CRITICAL_ASSET_1648220220216","entityName":"35L_DEP","droneId":"RvwembwLgIdcb5W1WWmU","droneName":"Drone_01","eventType":"DRONE_VS_CA","description":"drone vs critical asset","riskType":"RED","distance":1112.67,"timestamp":1549642413000,"visible":true,"id":"6272468f81a14320800b63ca"},{"entityId":"CRITICAL_ASSET_1648217782833","entityName":"R35L","droneId":"nX6JBA3QdiTF5OnMP3gs","droneName":"Drone_03","eventType":"DRONE_VS_CA","description":"drone vs critical asset","riskType":"YELLOW","distance":1786.96,"timestamp":1549642440000,"visible":false,"id":"627246aa81a14320800b679c"},{"entityId":"CRITICAL_ASSET_1648220220216","entityName":"35L_DEP","droneId":"RvwembwLgIdcb5W1WWmU","droneName":"Drone_01","eventType":"DRONE_VS_CA","description":"drone vs critical asset","riskType":"RED","distance":842.7,"timestamp":1549642467000,"visible":false,"id":"627246c581a14320800b6b90"},{"entityId":"CRITICAL_ASSET_1648220220216","entityName":"35L_DEP","droneId":"RvwembwLgIdcb5W1WWmU","droneName":"Drone_01","eventType":"DRONE_VS_CA","description":"drone vs critical asset","riskType":"RED","distance":817.71,"timestamp":1549642472000,"visible":false,"id":"627246ca81a14320800b6c4c"},{"entityId":"CRITICAL_ASSET_1648220220216","entityName":"35L_DEP","droneId":"nX6JBA3QdiTF5OnMP3gs","droneName":"Drone_03","eventType":"DRONE_VS_CA","description":"drone vs critical asset","riskType":"YELLOW","distance":1191.97,"timestamp":1549642485000,"visible":true,"id":"627246d781a14320800b6e2e"},{"entityId":"CRITICAL_ASSET_1648220220216","entityName":"35L_DEP","droneId":"RvwembwLgIdcb5W1WWmU","droneName":"Drone_01","eventType":"DRONE_VS_CA","description":"drone vs critical asset","riskType":"RED","distance":697.73,"timestamp":1549642496000,"visible":true,"id":"627246e281a14320800b6fd2"},{"entityId":"CRITICAL_ASSET_1648220220216","entityName":"35L_DEP","droneId":"RvwembwLgIdcb5W1WWmU","droneName":"Drone_01","eventType":"DRONE_VS_CA","description":"drone vs critical asset","riskType":"RED","distance":607.75,"timestamp":1549642514000,"visible":true,"id":"627246f481a14320800b7270"},{"entityId":"CRITICAL_ASSET_1648220220216","entityName":"35L_DEP","droneId":"RvwembwLgIdcb5W1WWmU","droneName":"Drone_01","eventType":"DRONE_VS_CA","description":"drone vs critical asset","riskType":"RED","distance":567.77,"timestamp":1549642522000,"visible":true,"id":"627246fc81a14320800b7396"},{"entityId":"CRITICAL_ASSET_1648220220216","entityName":"35L_DEP","droneId":"RvwembwLgIdcb5W1WWmU","droneName":"Drone_01","eventType":"DRONE_VS_CA","description":"drone vs critical asset","riskType":"RED","distance":562.77,"timestamp":1549642523000,"visible":false,"id":"627246fd81a14320800b73bc"},{"entityId":"CRITICAL_ASSET_1648220220216","entityName":"35L_DEP","droneId":"RvwembwLgIdcb5W1WWmU","droneName":"Drone_01","eventType":"DRONE_VS_CA","description":"drone vs critical asset","riskType":"RED","distance":557.77,"timestamp":1549642524000,"visible":true,"id":"627246fe81a14320800b73e2"},{"entityId":"CRITICAL_ASSET_1648220220216","entityName":"35L_DEP","droneId":"RvwembwLgIdcb5W1WWmU","droneName":"Drone_01","eventType":"DRONE_VS_CA","description":"drone vs critical asset","riskType":"RED","distance":542.77,"timestamp":1549642527000,"visible":true,"id":"6272470181a14320800b7452"},{"entityId":"CRITICAL_ASSET_1648220220216","entityName":"35L_DEP","droneId":"RvwembwLgIdcb5W1WWmU","droneName":"Drone_01","eventType":"DRONE_VS_CA","description":"drone vs critical asset","riskType":"RED","distance":507.79,"timestamp":1549642534000,"visible":false,"id":"6272470881a14320800b7550"},{"entityId":"CRITICAL_ASSET_1648220220216","entityName":"35L_DEP","droneId":"RvwembwLgIdcb5W1WWmU","droneName":"Drone_01","eventType":"DRONE_VS_CA","description":"drone vs critical asset","riskType":"RED","distance":367.87,"timestamp":1549642562000,"visible":false,"id":"6272472481a14320800b7950"},{"entityId":"CRITICAL_ASSET_1648220220216","entityName":"35L_DEP","droneId":"RvwembwLgIdcb5W1WWmU","droneName":"Drone_01","eventType":"DRONE_VS_CA","description":"drone vs critical asset","riskType":"RED","distance":362.87,"timestamp":1549642563000,"visible":true,"id":"6272472581a14320800b7976"},{"entityId":"CRITICAL_ASSET_1648220220216","entityName":"35L_DEP","droneId":"RvwembwLgIdcb5W1WWmU","droneName":"Drone_01","eventType":"DRONE_VS_CA","description":"drone vs critical asset","riskType":"RED","distance":302.93,"timestamp":1549642575000,"visible":false,"id":"6272473181a14320800b7b30"},{"entityId":"CRITICAL_ASSET_1648220220216","entityName":"35L_DEP","droneId":"RvwembwLgIdcb5W1WWmU","droneName":"Drone_01","eventType":"DRONE_VS_CA","description":"drone vs critical asset","riskType":"RED","distance":297.94,"timestamp":1549642576000,"visible":true,"id":"6272473281a14320800b7b56"},{"entityId":"CRITICAL_ASSET_1648220220216","entityName":"35L_DEP","droneId":"RvwembwLgIdcb5W1WWmU","droneName":"Drone_01","eventType":"DRONE_VS_CA","description":"drone vs critical asset","riskType":"RED","distance":233.04,"timestamp":1549642589000,"visible":false,"id":"6272473f81a14320800b7d2c"},{"entityId":"CRITICAL_ASSET_1648220220216","entityName":"35L_DEP","droneId":"RvwembwLgIdcb5W1WWmU","droneName":"Drone_01","eventType":"DRONE_VS_CA","description":"drone vs critical asset","riskType":"RED","distance":163.23,"timestamp":1549642603000,"visible":true,"id":"6272474d81a14320800b7f2e"},{"entityId":"CRITICAL_ASSET_1648220220216","entityName":"35L_DEP","droneId":"RvwembwLgIdcb5W1WWmU","droneName":"Drone_01","eventType":"DRONE_VS_CA","description":"drone vs critical asset","riskType":"RED","distance":148.3,"timestamp":1549642606000,"visible":true,"id":"6272475081a14320800b7f9e"},{"entityId":"CRITICAL_ASSET_1648220220216","entityName":"35L_DEP","droneId":"RvwembwLgIdcb5W1WWmU","droneName":"Drone_01","eventType":"DRONE_VS_CA","description":"drone vs critical asset","riskType":"RED","distance":138.35,"timestamp":1549642608000,"visible":false,"id":"6272475281a14320800b7fe8"},{"entityId":"CRITICAL_ASSET_1648220220216","entityName":"35L_DEP","droneId":"RvwembwLgIdcb5W1WWmU","droneName":"Drone_01","eventType":"DRONE_VS_CA","description":"drone vs critical asset","riskType":"RED","distance":123.45,"timestamp":1549642611000,"visible":false,"id":"6272475581a14320800b805a"},{"entityId":"CRITICAL_ASSET_1648220220216","entityName":"35L_DEP","droneId":"RvwembwLgIdcb5W1WWmU","droneName":"Drone_01","eventType":"DRONE_VS_CA","description":"drone vs critical asset","riskType":"RED","distance":22.88,"timestamp":1549642632000,"visible":false,"id":"6272476a81a14320800b835e"},{"entityId":"CRITICAL_ASSET_1648220220216","entityName":"35L_DEP","droneId":"RvwembwLgIdcb5W1WWmU","droneName":"Drone_01","eventType":"DRONE_VS_CA","description":"drone vs critical asset","riskType":"RED","distance":143.18,"timestamp":1549642664000,"visible":true,"id":"6272478a81a14320800b87ec"},{"entityId":"CRITICAL_ASSET_1648220220216","entityName":"35L_DEP","droneId":"RvwembwLgIdcb5W1WWmU","droneName":"Drone_01","eventType":"DRONE_VS_CA","description":"drone vs critical asset","riskType":"RED","distance":212.93,"timestamp":1549642678000,"visible":false,"id":"6272479881a14320800b89f2"},{"entityId":"CRITICAL_ASSET_1648220220216","entityName":"35L_DEP","droneId":"RvwembwLgIdcb5W1WWmU","droneName":"Drone_01","eventType":"DRONE_VS_CA","description":"drone vs critical asset","riskType":"RED","distance":257.84,"timestamp":1549642687000,"visible":true,"id":"627247a181a14320800b8b3e"},{"entityId":"CRITICAL_ASSET_1648220220216","entityName":"35L_DEP","droneId":"RvwembwLgIdcb5W1WWmU","droneName":"Drone_01","eventType":"DRONE_VS_CA","description":"drone vs critical asset","riskType":"RED","distance":292.79,"timestamp":1549642694000,"visible":false,"id":"627247a881a14320800b8c32"},{"entityId":"CRITICAL_ASSET_1648217782833","entityName":"R35L","droneId":"RvwembwLgIdcb5W1WWmU","droneName":"Drone_01","eventType":"DRONE_VS_CA","description":"drone vs critical asset","riskType":"YELLOW","distance":2553.37,"timestamp":1549642701000,"visible":true,"id":"627247af81a14320800b8d28"},{"entityId":"CRITICAL_ASSET_1648220220216","entityName":"35L_DEP","droneId":"RvwembwLgIdcb5W1WWmU","droneName":"Drone_01","eventType":"DRONE_VS_CA","description":"drone vs critical asset","riskType":"RED","distance":402.69,"timestamp":1549642716000,"visible":false,"id":"627247be81a14320800b8f52"},{"entityId":"CRITICAL_ASSET_1648220220216","entityName":"35L_DEP","droneId":"RvwembwLgIdcb5W1WWmU","droneName":"Drone_01","eventType":"DRONE_VS_CA","description":"drone vs critical asset","riskType":"RED","distance":412.69,"timestamp":1549642718000,"visible":true,"id":"627247c081a14320800b8f9a"},{"entityId":"CRITICAL_ASSET_1648217782833","entityName":"R35L","droneId":"RvwembwLgIdcb5W1WWmU","droneName":"Drone_01","eventType":"DRONE_VS_CA","description":"drone vs critical asset","riskType":"YELLOW","distance":2398.4,"timestamp":1549642732000,"visible":false,"id":"627247ce81a14320800b9184"},{"entityId":"CRITICAL_ASSET_1648217782833","entityName":"R35L","droneId":"RvwembwLgIdcb5W1WWmU","droneName":"Drone_01","eventType":"DRONE_VS_CA","description":"drone vs critical asset","riskType":"YELLOW","distance":2273.43,"timestamp":1549642757000,"visible":false,"id":"627247e781a14320800b94fc"},{"entityId":"CRITICAL_ASSET_1648220220216","entityName":"35L_DEP","droneId":"RvwembwLgIdcb5W1WWmU","droneName":"Drone_01","eventType":"DRONE_VS_CA","description":"drone vs critical asset","riskType":"RED","distance":607.61,"timestamp":1549642757000,"visible":false,"id":"627247e781a14320800b94fe"},{"entityId":"CRITICAL_ASSET_1648220220216","entityName":"35L_DEP","droneId":"RvwembwLgIdcb5W1WWmU","droneName":"Drone_01","eventType":"DRONE_VS_CA","description":"drone vs critical asset","riskType":"RED","distance":697.58,"timestamp":1549642775000,"visible":true,"id":"627247f981a14320800b97a4"},{"entityId":"CRITICAL_ASSET_1648217782833","entityName":"R35L","droneId":"RvwembwLgIdcb5W1WWmU","droneName":"Drone_01","eventType":"DRONE_VS_CA","description":"drone vs critical asset","riskType":"YELLOW","distance":2168.46,"timestamp":1549642778000,"visible":false,"id":"627247fc81a14320800b9816"},{"entityId":"CRITICAL_ASSET_1648220220216","entityName":"35L_DEP","droneId":"RvwembwLgIdcb5W1WWmU","droneName":"Drone_01","eventType":"DRONE_VS_CA","description":"drone vs critical asset","riskType":"RED","distance":712.58,"timestamp":1549642778000,"visible":false,"id":"627247fc81a14320800b9818"},{"entityId":"CRITICAL_ASSET_1648217782833","entityName":"R35L","droneId":"RvwembwLgIdcb5W1WWmU","droneName":"Drone_01","eventType":"DRONE_VS_CA","description":"drone vs critical asset","riskType":"ORANGE","distance":2158.46,"timestamp":1549642780000,"visible":false,"id":"627247fe81a14320800b9868"},{"entityId":"CRITICAL_ASSET_1648217782833","entityName":"R35L","droneId":"RvwembwLgIdcb5W1WWmU","droneName":"Drone_01","eventType":"DRONE_VS_CA","description":"drone vs critical asset","riskType":"ORANGE","distance":2153.46,"timestamp":1549642781000,"visible":true,"id":"627247ff81a14320800b988e"},{"entityId":"CRITICAL_ASSET_1648220220216","entityName":"35L_DEP","droneId":"RvwembwLgIdcb5W1WWmU","droneName":"Drone_01","eventType":"DRONE_VS_CA","description":"drone vs critical asset","riskType":"RED","distance":727.58,"timestamp":1549642781000,"visible":true,"id":"627247ff81a14320800b9890"},{"entityId":"CRITICAL_ASSET_1648220220216","entityName":"35L_DEP","droneId":"RvwembwLgIdcb5W1WWmU","droneName":"Drone_01","eventType":"DRONE_VS_CA","description":"drone vs critical asset","riskType":"RED","distance":347.74,"timestamp":1549642705000,"visible":false,"id":"627247b381a14320800b8dbc"},{"entityId":"CRITICAL_ASSET_1648220220216","entityName":"35L_DEP","droneId":"RvwembwLgIdcb5W1WWmU","droneName":"Drone_01","eventType":"DRONE_VS_CA","description":"drone vs critical asset","riskType":"RED","distance":357.73,"timestamp":1549642707000,"visible":false,"id":"627247b581a14320800b8e06"},{"entityId":"CRITICAL_ASSET_1648217782833","entityName":"R35L","droneId":"RvwembwLgIdcb5W1WWmU","droneName":"Drone_01","eventType":"DRONE_VS_CA","description":"drone vs critical asset","riskType":"YELLOW","distance":2523.37,"timestamp":1549642707000,"visible":false,"id":"627247b581a14320800b8e08"},{"entityId":"CRITICAL_ASSET_1648220220216","entityName":"35L_DEP","droneId":"RvwembwLgIdcb5W1WWmU","droneName":"Drone_01","eventType":"DRONE_VS_CA","description":"drone vs critical asset","riskType":"RED","distance":362.72,"timestamp":1549642708000,"visible":true,"id":"627247b681a14320800b8e2c"},{"entityId":"CRITICAL_ASSET_1648220220216","entityName":"35L_DEP","droneId":"RvwembwLgIdcb5W1WWmU","droneName":"Drone_01","eventType":"DRONE_VS_CA","description":"drone vs critical asset","riskType":"RED","distance":422.68,"timestamp":1549642720000,"visible":true,"id":"627247c281a14320800b8fe6"},{"entityId":"CRITICAL_ASSET_1648220220216","entityName":"35L_DEP","droneId":"RvwembwLgIdcb5W1WWmU","droneName":"Drone_01","eventType":"DRONE_VS_CA","description":"drone vs critical asset","riskType":"RED","distance":472.65,"timestamp":1549642730000,"visible":true,"id":"627247cc81a14320800b9142"},{"entityId":"CRITICAL_ASSET_1648217782833","entityName":"R35L","droneId":"RvwembwLgIdcb5W1WWmU","droneName":"Drone_01","eventType":"DRONE_VS_CA","description":"drone vs critical asset","riskType":"YELLOW","distance":2343.41,"timestamp":1549642743000,"visible":true,"id":"627247d981a14320800b9300"},{"entityId":"CRITICAL_ASSET_1648220220216","entityName":"35L_DEP","droneId":"RvwembwLgIdcb5W1WWmU","droneName":"Drone_01","eventType":"DRONE_VS_CA","description":"drone vs critical asset","riskType":"RED","distance":617.6,"timestamp":1549642759000,"visible":true,"id":"627247e981a14320800b954a"},{"entityId":"CRITICAL_ASSET_1648217782833","entityName":"R35L","droneId":"RvwembwLgIdcb5W1WWmU","droneName":"Drone_01","eventType":"DRONE_VS_CA","description":"drone vs critical asset","riskType":"YELLOW","distance":2253.43,"timestamp":1549642761000,"visible":true,"id":"627247eb81a14320800b959a"},{"entityId":"CRITICAL_ASSET_1648217782833","entityName":"R35L","droneId":"RvwembwLgIdcb5W1WWmU","droneName":"Drone_01","eventType":"DRONE_VS_CA","description":"drone vs critical asset","riskType":"YELLOW","distance":2193.45,"timestamp":1549642773000,"visible":true,"id":"627247f781a14320800b9754"},{"entityId":"CRITICAL_ASSET_1648217782833","entityName":"R35L","droneId":"RvwembwLgIdcb5W1WWmU","droneName":"Drone_01","eventType":"DRONE_VS_CA","description":"drone vs critical asset","riskType":"YELLOW","distance":2163.46,"timestamp":1549642779000,"visible":true,"id":"627247fd81a14320800b983e"},{"entityId":"CRITICAL_ASSET_1648220220216","entityName":"35L_DEP","droneId":"RvwembwLgIdcb5W1WWmU","droneName":"Drone_01","eventType":"DRONE_VS_CA","description":"drone vs critical asset","riskType":"RED","distance":717.58,"timestamp":1549642779000,"visible":true,"id":"627247fd81a14320800b9840"},{"entityId":"CRITICAL_ASSET_1648220220216","entityName":"35L_DEP","droneId":"RvwembwLgIdcb5W1WWmU","droneName":"Drone_01","eventType":"DRONE_VS_CA","description":"drone vs critical asset","riskType":"RED","distance":742.57,"timestamp":1549642784000,"visible":false,"id":"6272480281a14320800b9900"},{"entityId":"CRITICAL_ASSET_1648218212724","entityName":"R35R","droneId":"Ybi96h1N3MxAHlwmMkoN","droneName":"Drone_02","eventType":"DRONE_VS_CA","description":"drone vs critical asset","riskType":"YELLOW","distance":1366.98,"timestamp":1549641207000,"visible":true,"id":"627241d981a14320800acfb8"},{"entityId":"CRITICAL_ASSET_1648218212724","entityName":"R35R","droneId":"Ybi96h1N3MxAHlwmMkoN","droneName":"Drone_02","eventType":"DRONE_VS_CA","description":"drone vs critical asset","riskType":"YELLOW","distance":1348.8,"timestamp":1549641218000,"visible":true,"id":"627241e481a14320800ad0b2"},{"entityId":"CRITICAL_ASSET_1648218212724","entityName":"R35R","droneId":"Ybi96h1N3MxAHlwmMkoN","droneName":"Drone_02","eventType":"DRONE_VS_CA","description":"drone vs critical asset","riskType":"YELLOW","distance":1339.39,"timestamp":1549641224000,"visible":false,"id":"627241ea81a14320800ad13a"},{"entityId":"CRITICAL_ASSET_1648218212724","entityName":"R35R","droneId":"Ybi96h1N3MxAHlwmMkoN","droneName":"Drone_02","eventType":"DRONE_VS_CA","description":"drone vs critical asset","riskType":"YELLOW","distance":1336.33,"timestamp":1549641226000,"visible":false,"id":"627241ec81a14320800ad16a"},{"entityId":"CRITICAL_ASSET_1648218212724","entityName":"R35R","droneId":"Ybi96h1N3MxAHlwmMkoN","droneName":"Drone_02","eventType":"DRONE_VS_CA","description":"drone vs critical asset","riskType":"YELLOW","distance":1333.32,"timestamp":1549641228000,"visible":true,"id":"627241ee81a14320800ad198"},{"entityId":"CRITICAL_ASSET_1648218212724","entityName":"R35R","droneId":"Ybi96h1N3MxAHlwmMkoN","droneName":"Drone_02","eventType":"DRONE_VS_CA","description":"drone vs critical asset","riskType":"YELLOW","distance":1310.71,"timestamp":1549641244000,"visible":false,"id":"627241fe81a14320800ad30e"},{"entityId":"CRITICAL_ASSET_1648218568249","entityName":"FINGER1","droneId":"8UMYEPnM84a7SSLnqZ95","droneName":"Drone_04","eventType":"DRONE_VS_CA","description":"drone vs critical asset","riskType":"RED","distance":23.93,"timestamp":1549641749000,"visible":false,"id":"627243f781a14320800b0758"},{"entityId":"CRITICAL_ASSET_1648218568249","entityName":"FINGER1","droneId":"8UMYEPnM84a7SSLnqZ95","droneName":"Drone_04","eventType":"DRONE_VS_CA","description":"drone vs critical asset","riskType":"RED","distance":25.26,"timestamp":1549641751000,"visible":false,"id":"627243f981a14320800b079c"},{"entityId":"CRITICAL_ASSET_1648218568249","entityName":"FINGER1","droneId":"8UMYEPnM84a7SSLnqZ95","droneName":"Drone_04","eventType":"DRONE_VS_CA","description":"drone vs critical asset","riskType":"RED","distance":32.07,"timestamp":1549641755000,"visible":true,"id":"627243fd81a14320800b081a"},{"entityId":"CRITICAL_ASSET_1648220220216","entityName":"35L_DEP","droneId":"RvwembwLgIdcb5W1WWmU","droneName":"Drone_01","eventType":"DRONE_VS_CA","description":"drone vs critical asset","riskType":"YELLOW","distance":1967.63,"timestamp":1549642242000,"visible":false,"id":"627245e481a14320800b4a04"},{"entityId":"CRITICAL_ASSET_1648220220216","entityName":"35L_DEP","droneId":"RvwembwLgIdcb5W1WWmU","droneName":"Drone_01","eventType":"DRONE_VS_CA","description":"drone vs critical asset","riskType":"YELLOW","distance":1957.63,"timestamp":1549642244000,"visible":false,"id":"627245e681a14320800b4a54"},{"entityId":"CRITICAL_ASSET_1648220220216","entityName":"35L_DEP","droneId":"RvwembwLgIdcb5W1WWmU","droneName":"Drone_01","eventType":"DRONE_VS_CA","description":"drone vs critical asset","riskType":"YELLOW","distance":1932.63,"timestamp":1549642249000,"visible":true,"id":"627245eb81a14320800b4b18"},{"entityId":"CRITICAL_ASSET_1648220220216","entityName":"35L_DEP","droneId":"RvwembwLgIdcb5W1WWmU","droneName":"Drone_01","eventType":"DRONE_VS_CA","description":"drone vs critical asset","riskType":"YELLOW","distance":1912.63,"timestamp":1549642253000,"visible":false,"id":"627245ef81a14320800b4bb2"},{"entityId":"CRITICAL_ASSET_1648220220216","entityName":"35L_DEP","droneId":"RvwembwLgIdcb5W1WWmU","droneName":"Drone_01","eventType":"DRONE_VS_CA","description":"drone vs critical asset","riskType":"YELLOW","distance":1857.63,"timestamp":1549642264000,"visible":false,"id":"627245fa81a14320800b4d62"},{"entityId":"CRITICAL_ASSET_1648220220216","entityName":"35L_DEP","droneId":"RvwembwLgIdcb5W1WWmU","droneName":"Drone_01","eventType":"DRONE_VS_CA","description":"drone vs critical asset","riskType":"YELLOW","distance":1797.63,"timestamp":1549642276000,"visible":true,"id":"6272460681a14320800b4f30"},{"entityId":"CRITICAL_ASSET_1648220220216","entityName":"35L_DEP","droneId":"RvwembwLgIdcb5W1WWmU","droneName":"Drone_01","eventType":"DRONE_VS_CA","description":"drone vs critical asset","riskType":"YELLOW","distance":1767.64,"timestamp":1549642282000,"visible":true,"id":"6272460c81a14320800b501e"},{"entityId":"CRITICAL_ASSET_1648220220216","entityName":"35L_DEP","droneId":"RvwembwLgIdcb5W1WWmU","droneName":"Drone_01","eventType":"DRONE_VS_CA","description":"drone vs critical asset","riskType":"YELLOW","distance":1717.64,"timestamp":1549642292000,"visible":true,"id":"6272461681a14320800b51a4"},{"entityId":"CRITICAL_ASSET_1648220220216","entityName":"35L_DEP","droneId":"RvwembwLgIdcb5W1WWmU","droneName":"Drone_01","eventType":"DRONE_VS_CA","description":"drone vs critical asset","riskType":"YELLOW","distance":1667.64,"timestamp":1549642302000,"visible":false,"id":"6272462081a14320800b5334"},{"entityId":"CRITICAL_ASSET_1648220220216","entityName":"35L_DEP","droneId":"RvwembwLgIdcb5W1WWmU","droneName":"Drone_01","eventType":"DRONE_VS_CA","description":"drone vs critical asset","riskType":"YELLOW","distance":1652.64,"timestamp":1549642305000,"visible":false,"id":"6272462381a14320800b53aa"},{"entityId":"CRITICAL_ASSET_1648220220216","entityName":"35L_DEP","droneId":"RvwembwLgIdcb5W1WWmU","droneName":"Drone_01","eventType":"DRONE_VS_CA","description":"drone vs critical asset","riskType":"ORANGE","distance":1452.65,"timestamp":1549642345000,"visible":false,"id":"6272464b81a14320800b59ca"},{"entityId":"CRITICAL_ASSET_1648220220216","entityName":"35L_DEP","droneId":"RvwembwLgIdcb5W1WWmU","droneName":"Drone_01","eventType":"DRONE_VS_CA","description":"drone vs critical asset","riskType":"ORANGE","distance":1437.65,"timestamp":1549642348000,"visible":true,"id":"6272464e81a14320800b5a44"},{"entityId":"CRITICAL_ASSET_1648220220216","entityName":"35L_DEP","droneId":"RvwembwLgIdcb5W1WWmU","droneName":"Drone_01","eventType":"DRONE_VS_CA","description":"drone vs critical asset","riskType":"ORANGE","distance":1422.65,"timestamp":1549642351000,"visible":false,"id":"6272465181a14320800b5aba"},{"entityId":"CRITICAL_ASSET_1648220220216","entityName":"35L_DEP","droneId":"RvwembwLgIdcb5W1WWmU","droneName":"Drone_01","eventType":"DRONE_VS_CA","description":"drone vs critical asset","riskType":"ORANGE","distance":1417.65,"timestamp":1549642352000,"visible":true,"id":"6272465281a14320800b5ae2"},{"entityId":"CRITICAL_ASSET_1648220220216","entityName":"35L_DEP","droneId":"RvwembwLgIdcb5W1WWmU","droneName":"Drone_01","eventType":"DRONE_VS_CA","description":"drone vs critical asset","riskType":"RED","distance":1367.65,"timestamp":1549642362000,"visible":false,"id":"6272465c81a14320800b5c64"},{"entityId":"CRITICAL_ASSET_1648220220216","entityName":"35L_DEP","droneId":"RvwembwLgIdcb5W1WWmU","droneName":"Drone_01","eventType":"DRONE_VS_CA","description":"drone vs critical asset","riskType":"RED","distance":1347.66,"timestamp":1549642366000,"visible":false,"id":"6272466081a14320800b5d04"},{"entityId":"CRITICAL_ASSET_1648220220216","entityName":"35L_DEP","droneId":"RvwembwLgIdcb5W1WWmU","droneName":"Drone_01","eventType":"DRONE_VS_CA","description":"drone vs critical asset","riskType":"RED","distance":1342.66,"timestamp":1549642367000,"visible":true,"id":"6272466181a14320800b5d2c"},{"entityId":"CRITICAL_ASSET_1648220220216","entityName":"35L_DEP","droneId":"RvwembwLgIdcb5W1WWmU","droneName":"Drone_01","eventType":"DRONE_VS_CA","description":"drone vs critical asset","riskType":"RED","distance":1262.66,"timestamp":1549642383000,"visible":false,"id":"6272467181a14320800b5f7a"},{"entityId":"CRITICAL_ASSET_1648220220216","entityName":"35L_DEP","droneId":"RvwembwLgIdcb5W1WWmU","droneName":"Drone_01","eventType":"DRONE_VS_CA","description":"drone vs critical asset","riskType":"RED","distance":957.69,"timestamp":1549642444000,"visible":true,"id":"627246ae81a14320800b6830"},{"entityId":"CRITICAL_ASSET_1648220220216","entityName":"35L_DEP","droneId":"RvwembwLgIdcb5W1WWmU","droneName":"Drone_01","eventType":"DRONE_VS_CA","description":"drone vs critical asset","riskType":"RED","distance":947.69,"timestamp":1549642446000,"visible":false,"id":"627246b081a14320800b6880"},{"entityId":"CRITICAL_ASSET_1648220220216","entityName":"35L_DEP","droneId":"nX6JBA3QdiTF5OnMP3gs","droneName":"Drone_03","eventType":"DRONE_VS_CA","description":"drone vs critical asset","riskType":"YELLOW","distance":1231.34,"timestamp":1549642447000,"visible":false,"id":"627246b181a14320800b68a8"},{"entityId":"CRITICAL_ASSET_1648220220216","entityName":"35L_DEP","droneId":"RvwembwLgIdcb5W1WWmU","droneName":"Drone_01","eventType":"DRONE_VS_CA","description":"drone vs critical asset","riskType":"RED","distance":922.69,"timestamp":1549642451000,"visible":false,"id":"627246b581a14320800b6940"},{"entityId":"CRITICAL_ASSET_1648220220216","entityName":"35L_DEP","droneId":"RvwembwLgIdcb5W1WWmU","droneName":"Drone_01","eventType":"DRONE_VS_CA","description":"drone vs critical asset","riskType":"RED","distance":897.7,"timestamp":1549642456000,"visible":false,"id":"627246ba81a14320800b69f8"},{"entityId":"CRITICAL_ASSET_1648220220216","entityName":"35L_DEP","droneId":"RvwembwLgIdcb5W1WWmU","droneName":"Drone_01","eventType":"DRONE_VS_CA","description":"drone vs critical asset","riskType":"RED","distance":867.7,"timestamp":1549642462000,"visible":true,"id":"627246c081a14320800b6ad6"},{"entityId":"CRITICAL_ASSET_1648220220216","entityName":"35L_DEP","droneId":"RvwembwLgIdcb5W1WWmU","droneName":"Drone_01","eventType":"DRONE_VS_CA","description":"drone vs critical asset","riskType":"RED","distance":847.7,"timestamp":1549642466000,"visible":true,"id":"627246c481a14320800b6b6a"},{"entityId":"CRITICAL_ASSET_1648220220216","entityName":"35L_DEP","droneId":"RvwembwLgIdcb5W1WWmU","droneName":"Drone_01","eventType":"DRONE_VS_CA","description":"drone vs critical asset","riskType":"RED","distance":802.71,"timestamp":1549642475000,"visible":true,"id":"627246cd81a14320800b6cbe"},{"entityId":"CRITICAL_ASSET_1648217782833","entityName":"R35L","droneId":"nX6JBA3QdiTF5OnMP3gs","droneName":"Drone_03","eventType":"DRONE_VS_CA","description":"drone vs critical asset","riskType":"YELLOW","distance":1762.06,"timestamp":1549642485000,"visible":true,"id":"627246d781a14320800b6e2c"},{"entityId":"CRITICAL_ASSET_1648217782833","entityName":"R35L","droneId":"nX6JBA3QdiTF5OnMP3gs","droneName":"Drone_03","eventType":"DRONE_VS_CA","description":"drone vs critical asset","riskType":"YELLOW","distance":1761.63,"timestamp":1549642486000,"visible":false,"id":"627246d881a14320800b6e54"},{"entityId":"CRITICAL_ASSET_1648220220216","entityName":"35L_DEP","droneId":"nX6JBA3QdiTF5OnMP3gs","droneName":"Drone_03","eventType":"DRONE_VS_CA","description":"drone vs critical asset","riskType":"YELLOW","distance":1191.05,"timestamp":1549642486000,"visible":false,"id":"627246d881a14320800b6e56"},{"entityId":"CRITICAL_ASSET_1648220220216","entityName":"35L_DEP","droneId":"RvwembwLgIdcb5W1WWmU","droneName":"Drone_01","eventType":"DRONE_VS_CA","description":"drone vs critical asset","riskType":"RED","distance":727.72,"timestamp":1549642490000,"visible":false,"id":"627246dc81a14320800b6eec"},{"entityId":"CRITICAL_ASSET_1648220220216","entityName":"35L_DEP","droneId":"RvwembwLgIdcb5W1WWmU","droneName":"Drone_01","eventType":"DRONE_VS_CA","description":"drone vs critical asset","riskType":"RED","distance":717.73,"timestamp":1549642492000,"visible":true,"id":"627246de81a14320800b6f36"},{"entityId":"CRITICAL_ASSET_1648220220216","entityName":"35L_DEP","droneId":"RvwembwLgIdcb5W1WWmU","droneName":"Drone_01","eventType":"DRONE_VS_CA","description":"drone vs critical asset","riskType":"RED","distance":702.73,"timestamp":1549642495000,"visible":false,"id":"627246e181a14320800b6fac"},{"entityId":"CRITICAL_ASSET_1648220220216","entityName":"35L_DEP","droneId":"RvwembwLgIdcb5W1WWmU","droneName":"Drone_01","eventType":"DRONE_VS_CA","description":"drone vs critical asset","riskType":"RED","distance":687.73,"timestamp":1549642498000,"visible":true,"id":"627246e481a14320800b701e"},{"entityId":"CRITICAL_ASSET_1648220220216","entityName":"35L_DEP","droneId":"RvwembwLgIdcb5W1WWmU","droneName":"Drone_01","eventType":"DRONE_VS_CA","description":"drone vs critical asset","riskType":"RED","distance":662.74,"timestamp":1549642503000,"visible":false,"id":"627246e981a14320800b70d6"},{"entityId":"CRITICAL_ASSET_1648220220216","entityName":"35L_DEP","droneId":"RvwembwLgIdcb5W1WWmU","droneName":"Drone_01","eventType":"DRONE_VS_CA","description":"drone vs critical asset","riskType":"RED","distance":572.76,"timestamp":1549642521000,"visible":false,"id":"627246fb81a14320800b7370"},{"entityId":"CRITICAL_ASSET_1648220220216","entityName":"35L_DEP","droneId":"RvwembwLgIdcb5W1WWmU","droneName":"Drone_01","eventType":"DRONE_VS_CA","description":"drone vs critical asset","riskType":"RED","distance":552.77,"timestamp":1549642525000,"visible":false,"id":"627246ff81a14320800b7408"},{"entityId":"CRITICAL_ASSET_1648220220216","entityName":"35L_DEP","droneId":"RvwembwLgIdcb5W1WWmU","droneName":"Drone_01","eventType":"DRONE_VS_CA","description":"drone vs critical asset","riskType":"RED","distance":482.8,"timestamp":1549642539000,"visible":false,"id":"6272470d81a14320800b7608"},{"entityId":"CRITICAL_ASSET_1648220220216","entityName":"35L_DEP","droneId":"RvwembwLgIdcb5W1WWmU","droneName":"Drone_01","eventType":"DRONE_VS_CA","description":"drone vs critical asset","riskType":"RED","distance":472.8,"timestamp":1549642541000,"visible":true,"id":"6272470f81a14320800b7652"},{"entityId":"CRITICAL_ASSET_1648220220216","entityName":"35L_DEP","droneId":"RvwembwLgIdcb5W1WWmU","droneName":"Drone_01","eventType":"DRONE_VS_CA","description":"drone vs critical asset","riskType":"RED","distance":437.82,"timestamp":1549642548000,"visible":true,"id":"6272471681a14320800b7752"},{"entityId":"CRITICAL_ASSET_1648220220216","entityName":"35L_DEP","droneId":"RvwembwLgIdcb5W1WWmU","droneName":"Drone_01","eventType":"DRONE_VS_CA","description":"drone vs critical asset","riskType":"RED","distance":357.88,"timestamp":1549642564000,"visible":false,"id":"6272472681a14320800b799c"},{"entityId":"CRITICAL_ASSET_1648220220216","entityName":"35L_DEP","droneId":"RvwembwLgIdcb5W1WWmU","droneName":"Drone_01","eventType":"DRONE_VS_CA","description":"drone vs critical asset","riskType":"RED","distance":352.88,"timestamp":1549642565000,"visible":true,"id":"6272472781a14320800b79c2"},{"entityId":"CRITICAL_ASSET_1648220220216","entityName":"35L_DEP","droneId":"RvwembwLgIdcb5W1WWmU","droneName":"Drone_01","eventType":"DRONE_VS_CA","description":"drone vs critical asset","riskType":"RED","distance":312.92,"timestamp":1549642573000,"visible":true,"id":"6272472f81a14320800b7ae6"},{"entityId":"CRITICAL_ASSET_1648220220216","entityName":"35L_DEP","droneId":"RvwembwLgIdcb5W1WWmU","droneName":"Drone_01","eventType":"DRONE_VS_CA","description":"drone vs critical asset","riskType":"RED","distance":168.21,"timestamp":1549642602000,"visible":false,"id":"6272474c81a14320800b7f08"},{"entityId":"CRITICAL_ASSET_1648220220216","entityName":"35L_DEP","droneId":"RvwembwLgIdcb5W1WWmU","droneName":"Drone_01","eventType":"DRONE_VS_CA","description":"drone vs critical asset","riskType":"RED","distance":98.67,"timestamp":1549642616000,"visible":true,"id":"6272475a81a14320800b8114"},{"entityId":"CRITICAL_ASSET_1648220220216","entityName":"35L_DEP","droneId":"RvwembwLgIdcb5W1WWmU","droneName":"Drone_01","eventType":"DRONE_VS_CA","description":"drone vs critical asset","riskType":"RED","distance":44.88,"timestamp":1549642644000,"visible":false,"id":"6272477681a14320800b8512"},{"entityId":"CRITICAL_ASSET_1648220220216","entityName":"35L_DEP","droneId":"RvwembwLgIdcb5W1WWmU","droneName":"Drone_01","eventType":"DRONE_VS_CA","description":"drone vs critical asset","riskType":"RED","distance":49.63,"timestamp":1549642645000,"visible":true,"id":"6272477781a14320800b8538"},{"entityId":"CRITICAL_ASSET_1648220220216","entityName":"35L_DEP","droneId":"RvwembwLgIdcb5W1WWmU","droneName":"Drone_01","eventType":"DRONE_VS_CA","description":"drone vs critical asset","riskType":"RED","distance":192.98,"timestamp":1549642674000,"visible":true,"id":"6272479481a14320800b8960"},{"entityId":"CRITICAL_ASSET_1648220220216","entityName":"35L_DEP","droneId":"RvwembwLgIdcb5W1WWmU","droneName":"Drone_01","eventType":"DRONE_VS_CA","description":"drone vs critical asset","riskType":"RED","distance":217.92,"timestamp":1549642679000,"visible":true,"id":"6272479981a14320800b8a18"},{"entityId":"CRITICAL_ASSET_1648220220216","entityName":"35L_DEP","droneId":"RvwembwLgIdcb5W1WWmU","droneName":"Drone_01","eventType":"DRONE_VS_CA","description":"drone vs critical asset","riskType":"RED","distance":227.9,"timestamp":1549642681000,"visible":true,"id":"6272479b81a14320800b8a64"},{"entityId":"CRITICAL_ASSET_1648220220216","entityName":"35L_DEP","droneId":"RvwembwLgIdcb5W1WWmU","droneName":"Drone_01","eventType":"DRONE_VS_CA","description":"drone vs critical asset","riskType":"RED","distance":332.75,"timestamp":1549642702000,"visible":false,"id":"627247b081a14320800b8d4e"},{"entityId":"CRITICAL_ASSET_1648220220216","entityName":"35L_DEP","droneId":"RvwembwLgIdcb5W1WWmU","droneName":"Drone_01","eventType":"DRONE_VS_CA","description":"drone vs critical asset","riskType":"RED","distance":382.71,"timestamp":1549642712000,"visible":false,"id":"627247ba81a14320800b8eb8"},{"entityId":"CRITICAL_ASSET_1648217782833","entityName":"R35L","droneId":"RvwembwLgIdcb5W1WWmU","droneName":"Drone_01","eventType":"DRONE_VS_CA","description":"drone vs critical asset","riskType":"YELLOW","distance":2498.38,"timestamp":1549642712000,"visible":false,"id":"627247ba81a14320800b8eba"},{"entityId":"CRITICAL_ASSET_1648220220216","entityName":"35L_DEP","droneId":"RvwembwLgIdcb5W1WWmU","droneName":"Drone_01","eventType":"DRONE_VS_CA","description":"drone vs critical asset","riskType":"RED","distance":392.7,"timestamp":1549642714000,"visible":false,"id":"627247bc81a14320800b8f04"},{"entityId":"CRITICAL_ASSET_1648217782833","entityName":"R35L","droneId":"RvwembwLgIdcb5W1WWmU","droneName":"Drone_01","eventType":"DRONE_VS_CA","description":"drone vs critical asset","riskType":"YELLOW","distance":2488.38,"timestamp":1549642714000,"visible":false,"id":"627247bc81a14320800b8f06"},{"entityId":"CRITICAL_ASSET_1648220220216","entityName":"35L_DEP","droneId":"RvwembwLgIdcb5W1WWmU","droneName":"Drone_01","eventType":"DRONE_VS_CA","description":"drone vs critical asset","riskType":"RED","distance":397.7,"timestamp":1549642715000,"visible":true,"id":"627247bd81a14320800b8f2a"},{"entityId":"CRITICAL_ASSET_1648217782833","entityName":"R35L","droneId":"RvwembwLgIdcb5W1WWmU","droneName":"Drone_01","eventType":"DRONE_VS_CA","description":"drone vs critical asset","riskType":"YELLOW","distance":2463.38,"timestamp":1549642719000,"visible":false,"id":"627247c181a14320800b8fbe"},{"entityId":"CRITICAL_ASSET_1648218212724","entityName":"R35R","droneId":"Ybi96h1N3MxAHlwmMkoN","droneName":"Drone_02","eventType":"DRONE_VS_CA","description":"drone vs critical asset","riskType":"YELLOW","distance":1337.86,"timestamp":1549641225000,"visible":true,"id":"627241eb81a14320800ad152"},{"entityId":"CRITICAL_ASSET_1648218212724","entityName":"R35R","droneId":"Ybi96h1N3MxAHlwmMkoN","droneName":"Drone_02","eventType":"DRONE_VS_CA","description":"drone vs critical asset","riskType":"YELLOW","distance":1314.74,"timestamp":1549641241000,"visible":false,"id":"627241fb81a14320800ad2c2"},{"entityId":"CRITICAL_ASSET_1648218212724","entityName":"R35R","droneId":"Ybi96h1N3MxAHlwmMkoN","droneName":"Drone_02","eventType":"DRONE_VS_CA","description":"drone vs critical asset","riskType":"YELLOW","distance":1309.38,"timestamp":1549641245000,"visible":true,"id":"627241ff81a14320800ad32a"},{"entityId":"CRITICAL_ASSET_1648218212724","entityName":"R35R","droneId":"Ybi96h1N3MxAHlwmMkoN","droneName":"Drone_02","eventType":"DRONE_VS_CA","description":"drone vs critical asset","riskType":"YELLOW","distance":1300.43,"timestamp":1549641252000,"visible":false,"id":"6272420681a14320800ad3d6"},{"entityId":"CRITICAL_ASSET_1648218212724","entityName":"R35R","droneId":"Ybi96h1N3MxAHlwmMkoN","droneName":"Drone_02","eventType":"DRONE_VS_CA","description":"drone vs critical asset","riskType":"YELLOW","distance":1299.2,"timestamp":1549641253000,"visible":true,"id":"6272420781a14320800ad3f0"},{"entityId":"CRITICAL_ASSET_1648218568249","entityName":"FINGER1","droneId":"8UMYEPnM84a7SSLnqZ95","droneName":"Drone_04","eventType":"DRONE_VS_CA","description":"drone vs critical asset","riskType":"ORANGE","distance":45.62,"timestamp":1549641736000,"visible":true,"id":"627243ea81a14320800b05ca"},{"entityId":"CRITICAL_ASSET_1648218568249","entityName":"FINGER1","droneId":"8UMYEPnM84a7SSLnqZ95","droneName":"Drone_04","eventType":"DRONE_VS_CA","description":"drone vs critical asset","riskType":"RED","distance":29.96,"timestamp":1549641754000,"visible":false,"id":"627243fc81a14320800b07fa"},{"entityId":"CRITICAL_ASSET_1648220220216","entityName":"35L_DEP","droneId":"RvwembwLgIdcb5W1WWmU","droneName":"Drone_01","eventType":"DRONE_VS_CA","description":"drone vs critical asset","riskType":"YELLOW","distance":1972.63,"timestamp":1549642241000,"visible":true,"id":"627245e381a14320800b49dc"},{"entityId":"CRITICAL_ASSET_1648220220216","entityName":"35L_DEP","droneId":"RvwembwLgIdcb5W1WWmU","droneName":"Drone_01","eventType":"DRONE_VS_CA","description":"drone vs critical asset","riskType":"YELLOW","distance":1942.63,"timestamp":1549642247000,"visible":false,"id":"627245e981a14320800b4aca"},{"entityId":"CRITICAL_ASSET_1648220220216","entityName":"35L_DEP","droneId":"RvwembwLgIdcb5W1WWmU","droneName":"Drone_01","eventType":"DRONE_VS_CA","description":"drone vs critical asset","riskType":"YELLOW","distance":1892.63,"timestamp":1549642257000,"visible":true,"id":"627245f381a14320800b4c52"},{"entityId":"CRITICAL_ASSET_1648220220216","entityName":"35L_DEP","droneId":"RvwembwLgIdcb5W1WWmU","droneName":"Drone_01","eventType":"DRONE_VS_CA","description":"drone vs critical asset","riskType":"YELLOW","distance":1872.63,"timestamp":1549642261000,"visible":true,"id":"627245f781a14320800b4cee"},{"entityId":"CRITICAL_ASSET_1648220220216","entityName":"35L_DEP","droneId":"RvwembwLgIdcb5W1WWmU","droneName":"Drone_01","eventType":"DRONE_VS_CA","description":"drone vs critical asset","riskType":"YELLOW","distance":1782.63,"timestamp":1549642279000,"visible":false,"id":"6272460981a14320800b4fa4"},{"entityId":"CRITICAL_ASSET_1648220220216","entityName":"35L_DEP","droneId":"RvwembwLgIdcb5W1WWmU","droneName":"Drone_01","eventType":"DRONE_VS_CA","description":"drone vs critical asset","riskType":"YELLOW","distance":1777.63,"timestamp":1549642280000,"visible":true,"id":"6272460a81a14320800b4fcc"},{"entityId":"CRITICAL_ASSET_1648220220216","entityName":"35L_DEP","droneId":"RvwembwLgIdcb5W1WWmU","droneName":"Drone_01","eventType":"DRONE_VS_CA","description":"drone vs critical asset","riskType":"YELLOW","distance":1752.64,"timestamp":1549642285000,"visible":false,"id":"6272460f81a14320800b5092"},{"entityId":"CRITICAL_ASSET_1648220220216","entityName":"35L_DEP","droneId":"RvwembwLgIdcb5W1WWmU","droneName":"Drone_01","eventType":"DRONE_VS_CA","description":"drone vs critical asset","riskType":"YELLOW","distance":1747.64,"timestamp":1549642286000,"visible":true,"id":"6272461081a14320800b50ba"},{"entityId":"CRITICAL_ASSET_1648220220216","entityName":"35L_DEP","droneId":"RvwembwLgIdcb5W1WWmU","droneName":"Drone_01","eventType":"DRONE_VS_CA","description":"drone vs critical asset","riskType":"YELLOW","distance":1722.64,"timestamp":1549642291000,"visible":false,"id":"6272461581a14320800b517c"},{"entityId":"CRITICAL_ASSET_1648220220216","entityName":"35L_DEP","droneId":"RvwembwLgIdcb5W1WWmU","droneName":"Drone_01","eventType":"DRONE_VS_CA","description":"drone vs critical asset","riskType":"YELLOW","distance":1682.64,"timestamp":1549642299000,"visible":false,"id":"6272461d81a14320800b52be"},{"entityId":"CRITICAL_ASSET_1648220220216","entityName":"35L_DEP","droneId":"RvwembwLgIdcb5W1WWmU","droneName":"Drone_01","eventType":"DRONE_VS_CA","description":"drone vs critical asset","riskType":"YELLOW","distance":1672.64,"timestamp":1549642301000,"visible":true,"id":"6272461f81a14320800b530c"},{"entityId":"CRITICAL_ASSET_1648220220216","entityName":"35L_DEP","droneId":"RvwembwLgIdcb5W1WWmU","droneName":"Drone_01","eventType":"DRONE_VS_CA","description":"drone vs critical asset","riskType":"YELLOW","distance":1637.64,"timestamp":1549642308000,"visible":false,"id":"6272462681a14320800b5420"},{"entityId":"CRITICAL_ASSET_1648220220216","entityName":"35L_DEP","droneId":"RvwembwLgIdcb5W1WWmU","droneName":"Drone_01","eventType":"DRONE_VS_CA","description":"drone vs critical asset","riskType":"ORANGE","distance":1577.64,"timestamp":1549642320000,"visible":true,"id":"6272463281a14320800b55f6"},{"entityId":"CRITICAL_ASSET_1648220220216","entityName":"35L_DEP","droneId":"RvwembwLgIdcb5W1WWmU","droneName":"Drone_01","eventType":"DRONE_VS_CA","description":"drone vs critical asset","riskType":"ORANGE","distance":1542.64,"timestamp":1549642327000,"visible":true,"id":"6272463981a14320800b5706"},{"entityId":"CRITICAL_ASSET_1648220220216","entityName":"35L_DEP","droneId":"RvwembwLgIdcb5W1WWmU","droneName":"Drone_01","eventType":"DRONE_VS_CA","description":"drone vs critical asset","riskType":"ORANGE","distance":1527.65,"timestamp":1549642330000,"visible":false,"id":"6272463c81a14320800b577e"},{"entityId":"CRITICAL_ASSET_1648220220216","entityName":"35L_DEP","droneId":"RvwembwLgIdcb5W1WWmU","droneName":"Drone_01","eventType":"DRONE_VS_CA","description":"drone vs critical asset","riskType":"ORANGE","distance":1522.65,"timestamp":1549642331000,"visible":true,"id":"6272463d81a14320800b57a6"},{"entityId":"CRITICAL_ASSET_1648220220216","entityName":"35L_DEP","droneId":"RvwembwLgIdcb5W1WWmU","droneName":"Drone_01","eventType":"DRONE_VS_CA","description":"drone vs critical asset","riskType":"ORANGE","distance":1467.65,"timestamp":1549642342000,"visible":false,"id":"6272464881a14320800b5952"},{"entityId":"CRITICAL_ASSET_1648220220216","entityName":"35L_DEP","droneId":"RvwembwLgIdcb5W1WWmU","droneName":"Drone_01","eventType":"DRONE_VS_CA","description":"drone vs critical asset","riskType":"ORANGE","distance":1462.65,"timestamp":1549642343000,"visible":true,"id":"6272464981a14320800b597a"},{"entityId":"CRITICAL_ASSET_1648220220216","entityName":"35L_DEP","droneId":"RvwembwLgIdcb5W1WWmU","droneName":"Drone_01","eventType":"DRONE_VS_CA","description":"drone vs critical asset","riskType":"ORANGE","distance":1447.65,"timestamp":1549642346000,"visible":true,"id":"6272464c81a14320800b59f4"},{"entityId":"CRITICAL_ASSET_1648220220216","entityName":"35L_DEP","droneId":"RvwembwLgIdcb5W1WWmU","droneName":"Drone_01","eventType":"DRONE_VS_CA","description":"drone vs critical asset","riskType":"RED","distance":1202.67,"timestamp":1549642395000,"visible":false,"id":"6272467d81a14320800b6136"},{"entityId":"CRITICAL_ASSET_1648220220216","entityName":"35L_DEP","droneId":"RvwembwLgIdcb5W1WWmU","droneName":"Drone_01","eventType":"DRONE_VS_CA","description":"drone vs critical asset","riskType":"RED","distance":1177.67,"timestamp":1549642400000,"visible":false,"id":"6272468281a14320800b61ee"},{"entityId":"CRITICAL_ASSET_1648220220216","entityName":"35L_DEP","droneId":"RvwembwLgIdcb5W1WWmU","droneName":"Drone_01","eventType":"DRONE_VS_CA","description":"drone vs critical asset","riskType":"RED","distance":1172.67,"timestamp":1549642401000,"visible":true,"id":"6272468381a14320800b6214"},{"entityId":"CRITICAL_ASSET_1648220220216","entityName":"35L_DEP","droneId":"RvwembwLgIdcb5W1WWmU","droneName":"Drone_01","eventType":"DRONE_VS_CA","description":"drone vs critical asset","riskType":"RED","distance":1037.68,"timestamp":1549642428000,"visible":true,"id":"6272469e81a14320800b65ea"},{"entityId":"CRITICAL_ASSET_1648217782833","entityName":"R35L","droneId":"nX6JBA3QdiTF5OnMP3gs","droneName":"Drone_03","eventType":"DRONE_VS_CA","description":"drone vs critical asset","riskType":"YELLOW","distance":1782.42,"timestamp":1549642447000,"visible":false,"id":"627246b181a14320800b68a6"},{"entityId":"CRITICAL_ASSET_1648220220216","entityName":"35L_DEP","droneId":"RvwembwLgIdcb5W1WWmU","droneName":"Drone_01","eventType":"DRONE_VS_CA","description":"drone vs critical asset","riskType":"RED","distance":927.69,"timestamp":1549642450000,"visible":true,"id":"627246b481a14320800b691a"},{"entityId":"CRITICAL_ASSET_1648220220216","entityName":"35L_DEP","droneId":"RvwembwLgIdcb5W1WWmU","droneName":"Drone_01","eventType":"DRONE_VS_CA","description":"drone vs critical asset","riskType":"RED","distance":877.7,"timestamp":1549642460000,"visible":false,"id":"627246be81a14320800b6a8c"},{"entityId":"CRITICAL_ASSET_1648220220216","entityName":"35L_DEP","droneId":"RvwembwLgIdcb5W1WWmU","droneName":"Drone_01","eventType":"DRONE_VS_CA","description":"drone vs critical asset","riskType":"RED","distance":852.7,"timestamp":1549642465000,"visible":false,"id":"627246c381a14320800b6b44"},{"entityId":"CRITICAL_ASSET_1648220220216","entityName":"35L_DEP","droneId":"RvwembwLgIdcb5W1WWmU","droneName":"Drone_01","eventType":"DRONE_VS_CA","description":"drone vs critical asset","riskType":"RED","distance":837.7,"timestamp":1549642468000,"visible":true,"id":"627246c681a14320800b6bb6"},{"entityId":"CRITICAL_ASSET_1648220220216","entityName":"35L_DEP","droneId":"RvwembwLgIdcb5W1WWmU","droneName":"Drone_01","eventType":"DRONE_VS_CA","description":"drone vs critical asset","riskType":"RED","distance":827.71,"timestamp":1549642470000,"visible":true,"id":"627246c881a14320800b6c02"},{"entityId":"CRITICAL_ASSET_1648220220216","entityName":"35L_DEP","droneId":"RvwembwLgIdcb5W1WWmU","droneName":"Drone_01","eventType":"DRONE_VS_CA","description":"drone vs critical asset","riskType":"RED","distance":812.71,"timestamp":1549642473000,"visible":true,"id":"627246cb81a14320800b6c72"},{"entityId":"CRITICAL_ASSET_1648220220216","entityName":"35L_DEP","droneId":"RvwembwLgIdcb5W1WWmU","droneName":"Drone_01","eventType":"DRONE_VS_CA","description":"drone vs critical asset","riskType":"RED","distance":807.71,"timestamp":1549642474000,"visible":false,"id":"627246cc81a14320800b6c98"},{"entityId":"CRITICAL_ASSET_1648220220216","entityName":"35L_DEP","droneId":"RvwembwLgIdcb5W1WWmU","droneName":"Drone_01","eventType":"DRONE_VS_CA","description":"drone vs critical asset","riskType":"RED","distance":782.71,"timestamp":1549642479000,"visible":false,"id":"627246d181a14320800b6d50"},{"entityId":"CRITICAL_ASSET_1648220220216","entityName":"35L_DEP","droneId":"nX6JBA3QdiTF5OnMP3gs","droneName":"Drone_03","eventType":"DRONE_VS_CA","description":"drone vs critical asset","riskType":"YELLOW","distance":1189.25,"timestamp":1549642488000,"visible":true,"id":"627246da81a14320800b6ea0"},{"entityId":"CRITICAL_ASSET_1648220220216","entityName":"35L_DEP","droneId":"RvwembwLgIdcb5W1WWmU","droneName":"Drone_01","eventType":"DRONE_VS_CA","description":"drone vs critical asset","riskType":"RED","distance":692.73,"timestamp":1549642497000,"visible":false,"id":"627246e381a14320800b6ff8"},{"entityId":"CRITICAL_ASSET_1648220220216","entityName":"35L_DEP","droneId":"RvwembwLgIdcb5W1WWmU","droneName":"Drone_01","eventType":"DRONE_VS_CA","description":"drone vs critical asset","riskType":"RED","distance":502.79,"timestamp":1549642535000,"visible":true,"id":"6272470981a14320800b7576"},{"entityId":"CRITICAL_ASSET_1648220220216","entityName":"35L_DEP","droneId":"RvwembwLgIdcb5W1WWmU","droneName":"Drone_01","eventType":"DRONE_VS_CA","description":"drone vs critical asset","riskType":"RED","distance":447.82,"timestamp":1549642546000,"visible":false,"id":"6272471481a14320800b7708"},{"entityId":"CRITICAL_ASSET_1648220220216","entityName":"35L_DEP","droneId":"RvwembwLgIdcb5W1WWmU","droneName":"Drone_01","eventType":"DRONE_VS_CA","description":"drone vs critical asset","riskType":"RED","distance":402.84,"timestamp":1549642555000,"visible":true,"id":"6272471d81a14320800b7852"},{"entityId":"CRITICAL_ASSET_1648220220216","entityName":"35L_DEP","droneId":"RvwembwLgIdcb5W1WWmU","droneName":"Drone_01","eventType":"DRONE_VS_CA","description":"drone vs critical asset","riskType":"RED","distance":228.05,"timestamp":1549642590000,"visible":true,"id":"6272474081a14320800b7d52"},{"entityId":"CRITICAL_ASSET_1648220220216","entityName":"35L_DEP","droneId":"RvwembwLgIdcb5W1WWmU","droneName":"Drone_01","eventType":"DRONE_VS_CA","description":"drone vs critical asset","riskType":"RED","distance":133.38,"timestamp":1549642609000,"visible":true,"id":"6272475381a14320800b800e"},{"entityId":"CRITICAL_ASSET_1648220220216","entityName":"35L_DEP","droneId":"RvwembwLgIdcb5W1WWmU","droneName":"Drone_01","eventType":"DRONE_VS_CA","description":"drone vs critical asset","riskType":"RED","distance":69.14,"timestamp":1549642622000,"visible":false,"id":"6272476081a14320800b81ee"},{"entityId":"CRITICAL_ASSET_1648220220216","entityName":"35L_DEP","droneId":"RvwembwLgIdcb5W1WWmU","droneName":"Drone_01","eventType":"DRONE_VS_CA","description":"drone vs critical asset","riskType":"RED","distance":19.3,"timestamp":1549642633000,"visible":true,"id":"6272476b81a14320800b8384"},{"entityId":"CRITICAL_ASSET_1648220220216","entityName":"35L_DEP","droneId":"RvwembwLgIdcb5W1WWmU","droneName":"Drone_01","eventType":"DRONE_VS_CA","description":"drone vs critical asset","riskType":"RED","distance":133.23,"timestamp":1549642662000,"visible":false,"id":"6272478881a14320800b87a2"},{"entityId":"CRITICAL_ASSET_1648220220216","entityName":"35L_DEP","droneId":"RvwembwLgIdcb5W1WWmU","droneName":"Drone_01","eventType":"DRONE_VS_CA","description":"drone vs critical asset","riskType":"RED","distance":158.11,"timestamp":1549642667000,"visible":true,"id":"6272478d81a14320800b885c"},{"entityId":"CRITICAL_ASSET_1648220220216","entityName":"35L_DEP","droneId":"RvwembwLgIdcb5W1WWmU","droneName":"Drone_01","eventType":"DRONE_VS_CA","description":"drone vs critical asset","riskType":"RED","distance":168.07,"timestamp":1549642669000,"visible":true,"id":"6272478f81a14320800b88a8"},{"entityId":"CRITICAL_ASSET_1648220220216","entityName":"35L_DEP","droneId":"RvwembwLgIdcb5W1WWmU","droneName":"Drone_01","eventType":"DRONE_VS_CA","description":"drone vs critical asset","riskType":"RED","distance":237.88,"timestamp":1549642683000,"visible":false,"id":"6272479d81a14320800b8aae"},{"entityId":"CRITICAL_ASSET_1648220220216","entityName":"35L_DEP","droneId":"RvwembwLgIdcb5W1WWmU","droneName":"Drone_01","eventType":"DRONE_VS_CA","description":"drone vs critical asset","riskType":"RED","distance":252.85,"timestamp":1549642686000,"visible":false,"id":"627247a081a14320800b8b1a"},{"entityId":"CRITICAL_ASSET_1648220220216","entityName":"35L_DEP","droneId":"RvwembwLgIdcb5W1WWmU","droneName":"Drone_01","eventType":"DRONE_VS_CA","description":"drone vs critical asset","riskType":"RED","distance":267.83,"timestamp":1549642689000,"visible":false,"id":"627247a381a14320800b8b84"},{"entityId":"CRITICAL_ASSET_1648220220216","entityName":"35L_DEP","droneId":"RvwembwLgIdcb5W1WWmU","droneName":"Drone_01","eventType":"DRONE_VS_CA","description":"drone vs critical asset","riskType":"RED","distance":312.77,"timestamp":1549642698000,"visible":true,"id":"627247ac81a14320800b8cc0"},{"entityId":"CRITICAL_ASSET_1648217782833","entityName":"R35L","droneId":"RvwembwLgIdcb5W1WWmU","droneName":"Drone_01","eventType":"DRONE_VS_CA","description":"drone vs critical asset","riskType":"YELLOW","distance":2548.37,"timestamp":1549642702000,"visible":false,"id":"627247b081a14320800b8d4c"},{"entityId":"CRITICAL_ASSET_1648217782833","entityName":"R35L","droneId":"RvwembwLgIdcb5W1WWmU","droneName":"Drone_01","eventType":"DRONE_VS_CA","description":"drone vs critical asset","riskType":"YELLOW","distance":2538.37,"timestamp":1549642704000,"visible":true,"id":"627247b281a14320800b8d94"},{"entityId":"CRITICAL_ASSET_1648220220216","entityName":"35L_DEP","droneId":"RvwembwLgIdcb5W1WWmU","droneName":"Drone_01","eventType":"DRONE_VS_CA","description":"drone vs critical asset","riskType":"RED","distance":342.74,"timestamp":1549642704000,"visible":true,"id":"627247b281a14320800b8d96"},{"entityId":"CRITICAL_ASSET_1648217782833","entityName":"R35L","droneId":"RvwembwLgIdcb5W1WWmU","droneName":"Drone_01","eventType":"DRONE_VS_CA","description":"drone vs critical asset","riskType":"YELLOW","distance":2528.37,"timestamp":1549642706000,"visible":true,"id":"627247b481a14320800b8de0"},{"entityId":"CRITICAL_ASSET_1648220220216","entityName":"35L_DEP","droneId":"RvwembwLgIdcb5W1WWmU","droneName":"Drone_01","eventType":"DRONE_VS_CA","description":"drone vs critical asset","riskType":"RED","distance":352.73,"timestamp":1549642706000,"visible":true,"id":"627247b481a14320800b8de2"},{"entityId":"CRITICAL_ASSET_1648217782833","entityName":"R35L","droneId":"RvwembwLgIdcb5W1WWmU","droneName":"Drone_01","eventType":"DRONE_VS_CA","description":"drone vs critical asset","riskType":"YELLOW","distance":2518.37,"timestamp":1549642708000,"visible":true,"id":"627247b681a14320800b8e2e"},{"entityId":"CRITICAL_ASSET_1648220220216","entityName":"35L_DEP","droneId":"RvwembwLgIdcb5W1WWmU","droneName":"Drone_01","eventType":"DRONE_VS_CA","description":"drone vs critical asset","riskType":"RED","distance":387.7,"timestamp":1549642713000,"visible":true,"id":"627247bb81a14320800b8ede"},{"entityId":"CRITICAL_ASSET_1648217782833","entityName":"R35L","droneId":"RvwembwLgIdcb5W1WWmU","droneName":"Drone_01","eventType":"DRONE_VS_CA","description":"drone vs critical asset","riskType":"YELLOW","distance":2493.38,"timestamp":1549642713000,"visible":true,"id":"627247bb81a14320800b8ee0"},{"entityId":"CRITICAL_ASSET_1648217782833","entityName":"R35L","droneId":"RvwembwLgIdcb5W1WWmU","droneName":"Drone_01","eventType":"DRONE_VS_CA","description":"drone vs critical asset","riskType":"YELLOW","distance":2483.38,"timestamp":1549642715000,"visible":true,"id":"627247bd81a14320800b8f2c"},{"entityId":"CRITICAL_ASSET_1648217782833","entityName":"R35L","droneId":"RvwembwLgIdcb5W1WWmU","droneName":"Drone_01","eventType":"DRONE_VS_CA","description":"drone vs critical asset","riskType":"YELLOW","distance":2478.38,"timestamp":1549642716000,"visible":false,"id":"627247be81a14320800b8f50"},{"entityId":"CRITICAL_ASSET_1648220220216","entityName":"35L_DEP","droneId":"RvwembwLgIdcb5W1WWmU","droneName":"Drone_01","eventType":"DRONE_VS_CA","description":"drone vs critical asset","riskType":"RED","distance":417.68,"timestamp":1549642719000,"visible":false,"id":"627247c181a14320800b8fc0"},{"entityId":"CRITICAL_ASSET_1648217782833","entityName":"R35L","droneId":"RvwembwLgIdcb5W1WWmU","droneName":"Drone_01","eventType":"DRONE_VS_CA","description":"drone vs critical asset","riskType":"YELLOW","distance":2458.39,"timestamp":1549642720000,"visible":true,"id":"627247c281a14320800b8fe4"},{"entityId":"CRITICAL_ASSET_1648217782833","entityName":"R35L","droneId":"RvwembwLgIdcb5W1WWmU","droneName":"Drone_01","eventType":"DRONE_VS_CA","description":"drone vs critical asset","riskType":"YELLOW","distance":2413.4,"timestamp":1549642729000,"visible":false,"id":"627247cb81a14320800b9114"},{"entityId":"CRITICAL_ASSET_1648220220216","entityName":"35L_DEP","droneId":"RvwembwLgIdcb5W1WWmU","droneName":"Drone_01","eventType":"DRONE_VS_CA","description":"drone vs critical asset","riskType":"RED","distance":467.66,"timestamp":1549642729000,"visible":false,"id":"627247cb81a14320800b9116"},{"entityId":"CRITICAL_ASSET_1648217782833","entityName":"R35L","droneId":"RvwembwLgIdcb5W1WWmU","droneName":"Drone_01","eventType":"DRONE_VS_CA","description":"drone vs critical asset","riskType":"YELLOW","distance":2408.4,"timestamp":1549642730000,"visible":true,"id":"627247cc81a14320800b9140"},{"entityId":"CRITICAL_ASSET_1648220220216","entityName":"35L_DEP","droneId":"RvwembwLgIdcb5W1WWmU","droneName":"Drone_01","eventType":"DRONE_VS_CA","description":"drone vs critical asset","riskType":"RED","distance":482.65,"timestamp":1549642732000,"visible":false,"id":"627247ce81a14320800b9186"},{"entityId":"CRITICAL_ASSET_1648217782833","entityName":"R35L","droneId":"RvwembwLgIdcb5W1WWmU","droneName":"Drone_01","eventType":"DRONE_VS_CA","description":"drone vs critical asset","riskType":"YELLOW","distance":2393.4,"timestamp":1549642733000,"visible":true,"id":"627247cf81a14320800b91a8"},{"entityId":"CRITICAL_ASSET_1648220220216","entityName":"35L_DEP","droneId":"RvwembwLgIdcb5W1WWmU","droneName":"Drone_01","eventType":"DRONE_VS_CA","description":"drone vs critical asset","riskType":"RED","distance":487.65,"timestamp":1549642733000,"visible":true,"id":"627247cf81a14320800b91aa"},{"entityId":"CRITICAL_ASSET_1648220220216","entityName":"35L_DEP","droneId":"RvwembwLgIdcb5W1WWmU","droneName":"Drone_01","eventType":"DRONE_VS_CA","description":"drone vs critical asset","riskType":"RED","distance":532.63,"timestamp":1549642742000,"visible":false,"id":"627247d881a14320800b92d8"},{"entityId":"CRITICAL_ASSET_1648220220216","entityName":"35L_DEP","droneId":"RvwembwLgIdcb5W1WWmU","droneName":"Drone_01","eventType":"DRONE_VS_CA","description":"drone vs critical asset","riskType":"RED","distance":537.63,"timestamp":1549642743000,"visible":true,"id":"627247d981a14320800b9302"},{"entityId":"CRITICAL_ASSET_1648217782833","entityName":"R35L","droneId":"RvwembwLgIdcb5W1WWmU","droneName":"Drone_01","eventType":"DRONE_VS_CA","description":"drone vs critical asset","riskType":"YELLOW","distance":2263.43,"timestamp":1549642759000,"visible":true,"id":"627247e981a14320800b9548"},{"entityId":"CRITICAL_ASSET_1648217782833","entityName":"R35L","droneId":"RvwembwLgIdcb5W1WWmU","droneName":"Drone_01","eventType":"DRONE_VS_CA","description":"drone vs critical asset","riskType":"YELLOW","distance":2258.43,"timestamp":1549642760000,"visible":false,"id":"627247ea81a14320800b9572"},{"entityId":"CRITICAL_ASSET_1648220220216","entityName":"35L_DEP","droneId":"RvwembwLgIdcb5W1WWmU","droneName":"Drone_01","eventType":"DRONE_VS_CA","description":"drone vs critical asset","riskType":"RED","distance":682.59,"timestamp":1549642772000,"visible":false,"id":"627247f681a14320800b972c"},{"entityId":"CRITICAL_ASSET_1648217782833","entityName":"R35L","droneId":"RvwembwLgIdcb5W1WWmU","droneName":"Drone_01","eventType":"DRONE_VS_CA","description":"drone vs critical asset","riskType":"YELLOW","distance":2188.45,"timestamp":1549642774000,"visible":false,"id":"627247f881a14320800b977e"},{"entityId":"CRITICAL_ASSET_1648217782833","entityName":"R35L","droneId":"RvwembwLgIdcb5W1WWmU","droneName":"Drone_01","eventType":"DRONE_VS_CA","description":"drone vs critical asset","riskType":"YELLOW","distance":2183.45,"timestamp":1549642775000,"visible":true,"id":"627247f981a14320800b97a6"},{"entityId":"CRITICAL_ASSET_1648217782833","entityName":"R35L","droneId":"RvwembwLgIdcb5W1WWmU","droneName":"Drone_01","eventType":"DRONE_VS_CA","description":"drone vs critical asset","riskType":"ORANGE","distance":2138.47,"timestamp":1549642784000,"visible":false,"id":"6272480281a14320800b98fe"},{"entityId":"CRITICAL_ASSET_1648217782833","entityName":"R35L","droneId":"RvwembwLgIdcb5W1WWmU","droneName":"Drone_01","eventType":"DRONE_VS_CA","description":"drone vs critical asset","riskType":"YELLOW","distance":2468.38,"timestamp":1549642718000,"visible":true,"id":"627247c081a14320800b8f98"},{"entityId":"CRITICAL_ASSET_1648217782833","entityName":"R35L","droneId":"RvwembwLgIdcb5W1WWmU","droneName":"Drone_01","eventType":"DRONE_VS_CA","description":"drone vs critical asset","riskType":"YELLOW","distance":2348.41,"timestamp":1549642742000,"visible":false,"id":"627247d881a14320800b92da"},{"entityId":"CRITICAL_ASSET_1648220220216","entityName":"35L_DEP","droneId":"RvwembwLgIdcb5W1WWmU","droneName":"Drone_01","eventType":"DRONE_VS_CA","description":"drone vs critical asset","riskType":"RED","distance":622.6,"timestamp":1549642760000,"visible":false,"id":"627247ea81a14320800b9570"},{"entityId":"CRITICAL_ASSET_1648220220216","entityName":"35L_DEP","droneId":"RvwembwLgIdcb5W1WWmU","droneName":"Drone_01","eventType":"DRONE_VS_CA","description":"drone vs critical asset","riskType":"RED","distance":627.6,"timestamp":1549642761000,"visible":true,"id":"627247eb81a14320800b9598"},{"entityId":"CRITICAL_ASSET_1648217782833","entityName":"R35L","droneId":"RvwembwLgIdcb5W1WWmU","droneName":"Drone_01","eventType":"DRONE_VS_CA","description":"drone vs critical asset","riskType":"YELLOW","distance":2198.45,"timestamp":1549642772000,"visible":false,"id":"627247f681a14320800b972e"},{"entityId":"CRITICAL_ASSET_1648220220216","entityName":"35L_DEP","droneId":"RvwembwLgIdcb5W1WWmU","droneName":"Drone_01","eventType":"DRONE_VS_CA","description":"drone vs critical asset","riskType":"RED","distance":687.59,"timestamp":1549642773000,"visible":true,"id":"627247f781a14320800b9756"},{"entityId":"CRITICAL_ASSET_1648220220216","entityName":"35L_DEP","droneId":"RvwembwLgIdcb5W1WWmU","droneName":"Drone_01","eventType":"DRONE_VS_CA","description":"drone vs critical asset","riskType":"RED","distance":692.58,"timestamp":1549642774000,"visible":false,"id":"627247f881a14320800b977c"},{"entityId":"CRITICAL_ASSET_1648220220216","entityName":"35L_DEP","droneId":"RvwembwLgIdcb5W1WWmU","droneName":"Drone_01","eventType":"DRONE_VS_CA","description":"drone vs critical asset","riskType":"RED","distance":722.58,"timestamp":1549642780000,"visible":false,"id":"627247fe81a14320800b9866"}]